<?xml version="1.0" encoding="utf-8"?>
<CMPStudyConfig><EpochLength>30</EpochLength><StepChannels><StepChannel><Input>POSITION</Input><Labels><Label>RIGHT</Label><Label>LEFT</Label><Label>BACK</Label><Label>FRONT</Label></Labels></StepChannel><StepChannel><Input>LIGHT</Input><Labels><Label>ON</Label><Label>OFF</Label></Labels></StepChannel></StepChannels><ScoredEventSettings><ScoredEventSetting><Name>Central Apnea</Name><Colour>16689645</Colour><TextColour>4194304</TextColour><Input>ABDO RES</Input></ScoredEventSetting><ScoredEventSetting><Name>Obstructive Apnea</Name><Colour>16628921</Colour><TextColour>4194304</TextColour><Input>ABDO RES</Input></ScoredEventSetting><ScoredEventSetting><Name>Mixed Apnea</Name><Colour>16577711</Colour><TextColour>4194304</TextColour><Input>ABDO RES</Input></ScoredEventSetting><ScoredEventSetting><Name>SpO2 desaturation</Name><Colour>9342719</Colour><TextColour>4194304</TextColour><Input>SaO2</Input></ScoredEventSetting><ScoredEventSetting><Name>Respiratory artifact</Name><Colour>10406345</Colour><TextColour>4194304</TextColour><Input>ABDO RES</Input></ScoredEventSetting><ScoredEventSetting><Name>SpO2 artifact</Name><Colour>10406345</Colour><TextColour>4194304</TextColour><Input>SaO2</Input></ScoredEventSetting><ScoredEventSetting><Name>Arousal ()</Name><Colour>11206589</Colour><TextColour>4194304</TextColour><Input>EEG</Input></ScoredEventSetting><ScoredEventSetting><Name>Arousal ()</Name><Colour>11206589</Colour><TextColour>4194304</TextColour><Input>EEG</Input></ScoredEventSetting><ScoredEventSetting><Name>Arousal ()</Name><Colour>11206589</Colour><TextColour>4194304</TextColour><Input>EEG</Input></ScoredEventSetting><ScoredEventSetting><Name>Arousal ()</Name><Colour>11206589</Colour><TextColour>4194304</TextColour><Input>EEG</Input></ScoredEventSetting><ScoredEventSetting><Name>Arousal ()</Name><Colour>11206589</Colour><TextColour>4194304</TextColour><Input>EEG</Input></ScoredEventSetting><ScoredEventSetting><Name>PLM (Left)</Name><Colour>0</Colour><TextColour>0</TextColour></ScoredEventSetting><ScoredEventSetting><Name>Limb Movement (Left)</Name><Colour>0</Colour><TextColour>0</TextColour></ScoredEventSetting><ScoredEventSetting><Name>PLM (Right)</Name><Colour>0</Colour><TextColour>0</TextColour></ScoredEventSetting><ScoredEventSetting><Name>Limb Movement (Right)</Name><Colour>0</Colour><TextColour>0</TextColour></ScoredEventSetting><ScoredEventSetting><Name>Bradycardia</Name><Colour>16744576</Colour><TextColour>0</TextColour><Input>ECG</Input></ScoredEventSetting><ScoredEventSetting><Name>Tachycardia</Name><Colour>16744576</Colour><TextColour>0</TextColour><Input>ECG</Input></ScoredEventSetting><ScoredEventSetting><Name>TcCO2 artifact</Name><Colour>10406345</Colour><TextColour>4194304</TextColour></ScoredEventSetting><ScoredEventSetting><Name>EtCO2 artifact</Name><Colour>10406345</Colour><TextColour>4194304</TextColour></ScoredEventSetting><ScoredEventSetting><Name>Distal pH artifact</Name><Colour>10406345</Colour><TextColour>4194304</TextColour></ScoredEventSetting><ScoredEventSetting><Name>Distal pH</Name><Colour>8454143</Colour><TextColour>0</TextColour></ScoredEventSetting><ScoredEventSetting><Name>Proximal pH artifact</Name><Colour>10406345</Colour><TextColour>4194304</TextColour></ScoredEventSetting><ScoredEventSetting><Name>Proximal pH artifact</Name><Colour>8454143</Colour><TextColour>0</TextColour></ScoredEventSetting><ScoredEventSetting><Name>Blood pressure artifact</Name><Colour>10406345</Colour><TextColour>4194304</TextColour></ScoredEventSetting><ScoredEventSetting><Name>Body temperature artifact</Name><Colour>10406345</Colour><TextColour>4194304</TextColour></ScoredEventSetting><ScoredEventSetting><Name>Unsure</Name><Colour>11337727</Colour><TextColour>0</TextColour><Input>ABDO RES</Input></ScoredEventSetting><ScoredEventSetting><Name>Respiratory Paradox</Name><Colour>16711808</Colour><TextColour>0</TextColour><Input>THOR RES</Input></ScoredEventSetting><ScoredEventSetting><Name>Periodic Breathing</Name><Colour>16711808</Colour><TextColour>0</TextColour><Input>AIRFLOW</Input></ScoredEventSetting><ScoredEventSetting><Name>Periodic Breathing</Name><Colour>10406345</Colour><TextColour>4194304</TextColour><Input>ABDO RES</Input></ScoredEventSetting><ScoredEventSetting><Name>Obstructive Hypopnea</Name><Colour>16117971</Colour><TextColour>4194304</TextColour><Input>ABDO RES</Input></ScoredEventSetting><ScoredEventSetting><Name>Hypopnea</Name><Colour>16117971</Colour><TextColour>4194304</TextColour><Input>ABDO RES</Input></ScoredEventSetting><ScoredEventSetting><Name>Central Hypopnea</Name><Colour>16117971</Colour><TextColour>4194304</TextColour><Input>ABDO RES</Input></ScoredEventSetting><ScoredEventSetting><Name>Hypopnea</Name><Colour>16117971</Colour><TextColour>4194304</TextColour><Input>ABDO RES</Input></ScoredEventSetting><ScoredEventSetting><Name>Mixed Hypopnea</Name><Colour>16117971</Colour><TextColour>4194304</TextColour><Input>ABDO RES</Input></ScoredEventSetting><ScoredEventSetting><Name>Hypopnea</Name><Colour>16117971</Colour><TextColour>4194304</TextColour><Input>ABDO RES</Input></ScoredEventSetting><ScoredEventSetting><Name>RERA</Name><Colour>11206589</Colour><TextColour>4194304</TextColour><Input>ABDO RES</Input></ScoredEventSetting></ScoredEventSettings><ScoredEvents><ScoredEvent><Name>SpO2 artifact</Name><Start>130</Start><Duration>5</Duration><Input>SaO2</Input></ScoredEvent><ScoredEvent><Name>SpO2 artifact</Name><Start>1125</Start><Duration>4</Duration><Input>SaO2</Input></ScoredEvent><ScoredEvent><Name>SpO2 artifact</Name><Start>3414</Start><Duration>4</Duration><Input>SaO2</Input></ScoredEvent><ScoredEvent><Name>SpO2 artifact</Name><Start>3438</Start><Duration>7</Duration><Input>SaO2</Input></ScoredEvent><ScoredEvent><Name>SpO2 artifact</Name><Start>3535</Start><Duration>4</Duration><Input>SaO2</Input></ScoredEvent><ScoredEvent><Name>SpO2 artifact</Name><Start>3550</Start><Duration>9</Duration><Input>SaO2</Input></ScoredEvent><ScoredEvent><Name>SpO2 artifact</Name><Start>3570</Start><Duration>3</Duration><Input>SaO2</Input></ScoredEvent><ScoredEvent><Name>SpO2 artifact</Name><Start>3616</Start><Duration>10</Duration><Input>SaO2</Input></ScoredEvent><ScoredEvent><Name>SpO2 artifact</Name><Start>3695</Start><Duration>2</Duration><Input>SaO2</Input></ScoredEvent><ScoredEvent><Name>SpO2 artifact</Name><Start>3780</Start><Duration>29</Duration><Input>SaO2</Input></ScoredEvent><ScoredEvent><Name>SpO2 artifact</Name><Start>5300</Start><Duration>14</Duration><Input>SaO2</Input></ScoredEvent><ScoredEvent><Name>SpO2 artifact</Name><Start>5571</Start><Duration>5</Duration><Input>SaO2</Input></ScoredEvent><ScoredEvent><Name>SpO2 artifact</Name><Start>6407</Start><Duration>10</Duration><Input>SaO2</Input></ScoredEvent><ScoredEvent><Name>SpO2 artifact</Name><Start>7439</Start><Duration>6</Duration><Input>SaO2</Input></ScoredEvent><ScoredEvent><Name>SpO2 artifact</Name><Start>7518</Start><Duration>9</Duration><Input>SaO2</Input></ScoredEvent><ScoredEvent><Name>SpO2 artifact</Name><Start>8317</Start><Duration>10</Duration><Input>SaO2</Input></ScoredEvent><ScoredEvent><Name>SpO2 artifact</Name><Start>8428</Start><Duration>5</Duration><Input>SaO2</Input></ScoredEvent><ScoredEvent><Name>SpO2 artifact</Name><Start>8453</Start><Duration>3</Duration><Input>SaO2</Input></ScoredEvent><ScoredEvent><Name>SpO2 artifact</Name><Start>8505</Start><Duration>8</Duration><Input>SaO2</Input></ScoredEvent><ScoredEvent><Name>SpO2 artifact</Name><Start>8760</Start><Duration>5</Duration><Input>SaO2</Input></ScoredEvent><ScoredEvent><Name>SpO2 artifact</Name><Start>9063</Start><Duration>4</Duration><Input>SaO2</Input></ScoredEvent><ScoredEvent><Name>SpO2 artifact</Name><Start>9878</Start><Duration>12</Duration><Input>SaO2</Input></ScoredEvent><ScoredEvent><Name>Arousal ()</Name><Start>10427.6</Start><Duration>11.6</Duration><Input>EEG</Input></ScoredEvent><ScoredEvent><Name>Arousal ()</Name><Start>10559.4</Start><Duration>15.6</Duration><Input>EEG</Input></ScoredEvent><ScoredEvent><Name>Hypopnea</Name><Start>10630.7</Start><Duration>12.3</Duration><Input>ABDO RES</Input></ScoredEvent><ScoredEvent><Name>Arousal ()</Name><Start>10634.2</Start><Duration>8</Duration><Input>EEG</Input></ScoredEvent><ScoredEvent><LowestSpO2>92</LowestSpO2><Desaturation>2</Desaturation><Name>SpO2 desaturation</Name><Start>10660.7</Start><Duration>12.3</Duration><Input>SaO2</Input></ScoredEvent><ScoredEvent><Name>Arousal ()</Name><Start>10724</Start><Duration>16</Duration><Input>EEG</Input></ScoredEvent><ScoredEvent><Name>Hypopnea</Name><Start>13177.4</Start><Duration>21.5</Duration><Input>ABDO RES</Input></ScoredEvent><ScoredEvent><LowestSpO2>91</LowestSpO2><Desaturation>2</Desaturation><Name>SpO2 desaturation</Name><Start>13207.4</Start><Duration>21.5</Duration><Input>SaO2</Input></ScoredEvent><ScoredEvent><Name>Arousal ()</Name><Start>13259.6</Start><Duration>5.6</Duration><Input>EEG</Input></ScoredEvent><ScoredEvent><Name>Hypopnea</Name><Start>13288.1</Start><Duration>14.9</Duration><Input>ABDO RES</Input></ScoredEvent><ScoredEvent><Name>Arousal ()</Name><Start>13301.3</Start><Duration>4.7</Duration><Input>EEG</Input></ScoredEvent><ScoredEvent><Name>Arousal ()</Name><Start>13317.7</Start><Duration>17.3</Duration><Input>EEG</Input></ScoredEvent><ScoredEvent><Name>SpO2 artifact</Name><Start>13320.5</Start><Duration>80.5</Duration><Input>SaO2</Input></ScoredEvent><ScoredEvent><Name>Arousal ()</Name><Start>13510.1</Start><Duration>10.9</Duration><Input>EEG</Input></ScoredEvent><ScoredEvent><Name>Arousal ()</Name><Start>13565.4</Start><Duration>14.3</Duration><Input>EEG</Input></ScoredEvent><ScoredEvent><Name>Hypopnea</Name><Start>13603.9</Start><Duration>23.7</Duration><Input>ABDO RES</Input></ScoredEvent><ScoredEvent><LowestSpO2>89</LowestSpO2><Desaturation>4</Desaturation><Name>SpO2 desaturation</Name><Start>13633.9</Start><Duration>23.7</Duration><Input>SaO2</Input></ScoredEvent><ScoredEvent><Name>Hypopnea</Name><Start>13673.9</Start><Duration>20.5</Duration><Input>ABDO RES</Input></ScoredEvent><ScoredEvent><Name>Arousal ()</Name><Start>13689.4</Start><Duration>8.3</Duration><Input>EEG</Input></ScoredEvent><ScoredEvent><LowestSpO2>90</LowestSpO2><Desaturation>2</Desaturation><Name>SpO2 desaturation</Name><Start>13703.9</Start><Duration>20.5</Duration><Input>SaO2</Input></ScoredEvent><ScoredEvent><Name>Arousal ()</Name><Start>13712.4</Start><Duration>10.9</Duration><Input>EEG</Input></ScoredEvent><ScoredEvent><Name>Hypopnea</Name><Start>13749.5</Start><Duration>15.4</Duration><Input>ABDO RES</Input></ScoredEvent><ScoredEvent><LowestSpO2>88</LowestSpO2><Desaturation>5</Desaturation><Name>SpO2 desaturation</Name><Start>13779.5</Start><Duration>15.4</Duration><Input>SaO2</Input></ScoredEvent><ScoredEvent><Name>Hypopnea</Name><Start>13779.7</Start><Duration>17.9</Duration><Input>ABDO RES</Input></ScoredEvent><ScoredEvent><LowestSpO2>90</LowestSpO2><Desaturation>2</Desaturation><Name>SpO2 desaturation</Name><Start>13809.7</Start><Duration>17.9</Duration><Input>SaO2</Input></ScoredEvent><ScoredEvent><Name>Hypopnea</Name><Start>13834</Start><Duration>23.1</Duration><Input>ABDO RES</Input></ScoredEvent><ScoredEvent><LowestSpO2>89</LowestSpO2><Desaturation>4</Desaturation><Name>SpO2 desaturation</Name><Start>13864</Start><Duration>23.1</Duration><Input>SaO2</Input></ScoredEvent><ScoredEvent><Name>Arousal ()</Name><Start>13891.4</Start><Duration>24.2</Duration><Input>EEG</Input></ScoredEvent><ScoredEvent><Name>Hypopnea</Name><Start>13956.3</Start><Duration>13.3</Duration><Input>ABDO RES</Input></ScoredEvent><ScoredEvent><Name>Hypopnea</Name><Start>13982.6</Start><Duration>40.2</Duration><Input>ABDO RES</Input></ScoredEvent><ScoredEvent><LowestSpO2>92</LowestSpO2><Desaturation>2</Desaturation><Name>SpO2 desaturation</Name><Start>13986.3</Start><Duration>13.3</Duration><Input>SaO2</Input></ScoredEvent><ScoredEvent><LowestSpO2>91</LowestSpO2><Desaturation>2</Desaturation><Name>SpO2 desaturation</Name><Start>14012.6</Start><Duration>40.2</Duration><Input>SaO2</Input></ScoredEvent><ScoredEvent><Name>Hypopnea</Name><Start>14042.7</Start><Duration>25.6</Duration><Input>ABDO RES</Input></ScoredEvent><ScoredEvent><LowestSpO2>91</LowestSpO2><Desaturation>3</Desaturation><Name>SpO2 desaturation</Name><Start>14072.7</Start><Duration>25.6</Duration><Input>SaO2</Input></ScoredEvent><ScoredEvent><Name>Hypopnea</Name><Start>14083.7</Start><Duration>15.6</Duration><Input>ABDO RES</Input></ScoredEvent><ScoredEvent><Name>Arousal ()</Name><Start>14101.9</Start><Duration>8.1</Duration><Input>EEG</Input></ScoredEvent><ScoredEvent><LowestSpO2>89</LowestSpO2><Desaturation>3</Desaturation><Name>SpO2 desaturation</Name><Start>14113.7</Start><Duration>15.6</Duration><Input>SaO2</Input></ScoredEvent><ScoredEvent><Name>Hypopnea</Name><Start>14124.3</Start><Duration>39.1</Duration><Input>ABDO RES</Input></ScoredEvent><ScoredEvent><LowestSpO2>92</LowestSpO2><Desaturation>4</Desaturation><Name>SpO2 desaturation</Name><Start>14154.3</Start><Duration>39.1</Duration><Input>SaO2</Input></ScoredEvent><ScoredEvent><Name>Hypopnea</Name><Start>14170.6</Start><Duration>30.4</Duration><Input>ABDO RES</Input></ScoredEvent><ScoredEvent><LowestSpO2>91</LowestSpO2><Desaturation>2</Desaturation><Name>SpO2 desaturation</Name><Start>14200.6</Start><Duration>30.4</Duration><Input>SaO2</Input></ScoredEvent><ScoredEvent><Name>Hypopnea</Name><Start>14209</Start><Duration>16.1</Duration><Input>ABDO RES</Input></ScoredEvent><ScoredEvent><Name>Hypopnea</Name><Start>14236.9</Start><Duration>25.5</Duration><Input>ABDO RES</Input></ScoredEvent><ScoredEvent><LowestSpO2>91</LowestSpO2><Desaturation>2</Desaturation><Name>SpO2 desaturation</Name><Start>14239</Start><Duration>16.1</Duration><Input>SaO2</Input></ScoredEvent><ScoredEvent><Name>Arousal ()</Name><Start>14265.6</Start><Duration>7</Duration><Input>EEG</Input></ScoredEvent><ScoredEvent><LowestSpO2>92</LowestSpO2><Desaturation>1</Desaturation><Name>SpO2 desaturation</Name><Start>14266.9</Start><Duration>25.5</Duration><Input>SaO2</Input></ScoredEvent><ScoredEvent><Name>Hypopnea</Name><Start>14276.7</Start><Duration>16.4</Duration><Input>ABDO RES</Input></ScoredEvent><ScoredEvent><LowestSpO2>93</LowestSpO2><Desaturation>2</Desaturation><Name>SpO2 desaturation</Name><Start>14306.7</Start><Duration>16.4</Duration><Input>SaO2</Input></ScoredEvent><ScoredEvent><Name>Hypopnea</Name><Start>14314.1</Start><Duration>16.1</Duration><Input>ABDO RES</Input></ScoredEvent><ScoredEvent><LowestSpO2>93</LowestSpO2><Desaturation>1</Desaturation><Name>SpO2 desaturation</Name><Start>14344.1</Start><Duration>16.1</Duration><Input>SaO2</Input></ScoredEvent><ScoredEvent><Name>Hypopnea</Name><Start>14412</Start><Duration>66</Duration><Input>ABDO RES</Input></ScoredEvent><ScoredEvent><LowestSpO2>90</LowestSpO2><Desaturation>4</Desaturation><Name>SpO2 desaturation</Name><Start>14442</Start><Duration>66</Duration><Input>SaO2</Input></ScoredEvent><ScoredEvent><Name>Hypopnea</Name><Start>14509</Start><Duration>76.4</Duration><Input>ABDO RES</Input></ScoredEvent><ScoredEvent><LowestSpO2>91</LowestSpO2><Desaturation>3</Desaturation><Name>SpO2 desaturation</Name><Start>14539</Start><Duration>76.4</Duration><Input>SaO2</Input></ScoredEvent><ScoredEvent><Name>Hypopnea</Name><Start>14627.6</Start><Duration>19.2</Duration><Input>ABDO RES</Input></ScoredEvent><ScoredEvent><Name>Hypopnea</Name><Start>14651.4</Start><Duration>21.3</Duration><Input>ABDO RES</Input></ScoredEvent><ScoredEvent><LowestSpO2>92</LowestSpO2><Desaturation>3</Desaturation><Name>SpO2 desaturation</Name><Start>14657.6</Start><Duration>19.2</Duration><Input>SaO2</Input></ScoredEvent><ScoredEvent><LowestSpO2>92</LowestSpO2><Desaturation>3</Desaturation><Name>SpO2 desaturation</Name><Start>14681.4</Start><Duration>21.3</Duration><Input>SaO2</Input></ScoredEvent><ScoredEvent><Name>Arousal ()</Name><Start>14681.5</Start><Duration>4.6</Duration><Input>EEG</Input></ScoredEvent><ScoredEvent><Name>Hypopnea</Name><Start>14694</Start><Duration>47.3</Duration><Input>ABDO RES</Input></ScoredEvent><ScoredEvent><LowestSpO2>91</LowestSpO2><Desaturation>3</Desaturation><Name>SpO2 desaturation</Name><Start>14724</Start><Duration>47.3</Duration><Input>SaO2</Input></ScoredEvent><ScoredEvent><Name>Arousal ()</Name><Start>14742.6</Start><Duration>8.8</Duration><Input>EEG</Input></ScoredEvent><ScoredEvent><Name>Hypopnea</Name><Start>14754.6</Start><Duration>47.6</Duration><Input>ABDO RES</Input></ScoredEvent><ScoredEvent><LowestSpO2>92</LowestSpO2><Desaturation>4</Desaturation><Name>SpO2 desaturation</Name><Start>14784.6</Start><Duration>47.6</Duration><Input>SaO2</Input></ScoredEvent><ScoredEvent><Name>Hypopnea</Name><Start>14829.7</Start><Duration>13.8</Duration><Input>ABDO RES</Input></ScoredEvent><ScoredEvent><Name>Arousal ()</Name><Start>14842.7</Start><Duration>12</Duration><Input>EEG</Input></ScoredEvent><ScoredEvent><LowestSpO2>93</LowestSpO2><Desaturation>1</Desaturation><Name>SpO2 desaturation</Name><Start>14859.7</Start><Duration>13.8</Duration><Input>SaO2</Input></ScoredEvent><ScoredEvent><Name>Hypopnea</Name><Start>14865.2</Start><Duration>14.1</Duration><Input>ABDO RES</Input></ScoredEvent><ScoredEvent><LowestSpO2>93</LowestSpO2><Desaturation>3</Desaturation><Name>SpO2 desaturation</Name><Start>14895.2</Start><Duration>14.1</Duration><Input>SaO2</Input></ScoredEvent><ScoredEvent><Name>Hypopnea</Name><Start>14898.7</Start><Duration>18.2</Duration><Input>ABDO RES</Input></ScoredEvent><ScoredEvent><Name>Hypopnea</Name><Start>14925.3</Start><Duration>25.4</Duration><Input>ABDO RES</Input></ScoredEvent><ScoredEvent><LowestSpO2>93</LowestSpO2><Desaturation>1</Desaturation><Name>SpO2 desaturation</Name><Start>14928.7</Start><Duration>18.2</Duration><Input>SaO2</Input></ScoredEvent><ScoredEvent><LowestSpO2>93</LowestSpO2><Desaturation>1</Desaturation><Name>SpO2 desaturation</Name><Start>14955.3</Start><Duration>25.4</Duration><Input>SaO2</Input></ScoredEvent><ScoredEvent><Name>Hypopnea</Name><Start>14973</Start><Duration>23.6</Duration><Input>ABDO RES</Input></ScoredEvent><ScoredEvent><Name>Arousal ()</Name><Start>14990.9</Start><Duration>4.9</Duration><Input>EEG</Input></ScoredEvent><ScoredEvent><LowestSpO2>93</LowestSpO2><Desaturation>1</Desaturation><Name>SpO2 desaturation</Name><Start>15003</Start><Duration>23.6</Duration><Input>SaO2</Input></ScoredEvent><ScoredEvent><Name>Arousal ()</Name><Start>15024.8</Start><Duration>20.1</Duration><Input>EEG</Input></ScoredEvent><ScoredEvent><Name>Arousal ()</Name><Start>15079.2</Start><Duration>4.8</Duration><Input>EEG</Input></ScoredEvent><ScoredEvent><Name>Hypopnea</Name><Start>15107.4</Start><Duration>17.9</Duration><Input>ABDO RES</Input></ScoredEvent><ScoredEvent><LowestSpO2>92</LowestSpO2><Desaturation>2</Desaturation><Name>SpO2 desaturation</Name><Start>15137.4</Start><Duration>17.9</Duration><Input>SaO2</Input></ScoredEvent><ScoredEvent><Name>Arousal ()</Name><Start>15139.5</Start><Duration>4.7</Duration><Input>EEG</Input></ScoredEvent><ScoredEvent><Name>Arousal ()</Name><Start>15826.2</Start><Duration>6.5</Duration><Input>EEG</Input></ScoredEvent><ScoredEvent><Name>Arousal ()</Name><Start>16214.1</Start><Duration>7.2</Duration><Input>EEG</Input></ScoredEvent><ScoredEvent><Name>Arousal ()</Name><Start>16252</Start><Duration>3.4</Duration><Input>EEG</Input></ScoredEvent><ScoredEvent><Name>Hypopnea</Name><Start>16263.1</Start><Duration>16.8</Duration><Input>ABDO RES</Input></ScoredEvent><ScoredEvent><LowestSpO2>92</LowestSpO2><Desaturation>2</Desaturation><Name>SpO2 desaturation</Name><Start>16293.1</Start><Duration>16.8</Duration><Input>SaO2</Input></ScoredEvent><ScoredEvent><Name>Arousal ()</Name><Start>16406.8</Start><Duration>13.2</Duration><Input>EEG</Input></ScoredEvent><ScoredEvent><Name>Arousal ()</Name><Start>18221.8</Start><Duration>9.6</Duration><Input>EEG</Input></ScoredEvent><ScoredEvent><Name>Arousal ()</Name><Start>18258.6</Start><Duration>12.3</Duration><Input>EEG</Input></ScoredEvent><ScoredEvent><Name>Arousal ()</Name><Start>18300.6</Start><Duration>3.9</Duration><Input>EEG</Input></ScoredEvent><ScoredEvent><Name>Arousal ()</Name><Start>18321.8</Start><Duration>5.3</Duration><Input>EEG</Input></ScoredEvent><ScoredEvent><Name>Arousal ()</Name><Start>18352.4</Start><Duration>7.4</Duration><Input>EEG</Input></ScoredEvent><ScoredEvent><Name>Arousal ()</Name><Start>18396.6</Start><Duration>5</Duration><Input>EEG</Input></ScoredEvent><ScoredEvent><Name>Arousal ()</Name><Start>18482.2</Start><Duration>5.3</Duration><Input>EEG</Input></ScoredEvent><ScoredEvent><Name>Arousal ()</Name><Start>18523.6</Start><Duration>4.3</Duration><Input>EEG</Input></ScoredEvent><ScoredEvent><Name>Hypopnea</Name><Start>18609.1</Start><Duration>51.2</Duration><Input>ABDO RES</Input></ScoredEvent><ScoredEvent><LowestSpO2>91</LowestSpO2><Desaturation>2</Desaturation><Name>SpO2 desaturation</Name><Start>18639.1</Start><Duration>51.2</Duration><Input>SaO2</Input></ScoredEvent><ScoredEvent><Name>Central Apnea</Name><Start>18690.9</Start><Duration>13.3</Duration><Input>ABDO RES</Input></ScoredEvent><ScoredEvent><Name>Arousal ()</Name><Start>18714.1</Start><Duration>9.3</Duration><Input>EEG</Input></ScoredEvent><ScoredEvent><LowestSpO2>90</LowestSpO2><Desaturation>5</Desaturation><Name>SpO2 desaturation</Name><Start>18720.9</Start><Duration>13.3</Duration><Input>SaO2</Input></ScoredEvent><ScoredEvent><Name>Hypopnea</Name><Start>18746.1</Start><Duration>16.3</Duration><Input>ABDO RES</Input></ScoredEvent><ScoredEvent><LowestSpO2>91</LowestSpO2><Desaturation>4</Desaturation><Name>SpO2 desaturation</Name><Start>18776.1</Start><Duration>16.3</Duration><Input>SaO2</Input></ScoredEvent><ScoredEvent><Name>Arousal ()</Name><Start>18823.7</Start><Duration>5.3</Duration><Input>EEG</Input></ScoredEvent><ScoredEvent><Name>Hypopnea</Name><Start>18853</Start><Duration>13.8</Duration><Input>ABDO RES</Input></ScoredEvent><ScoredEvent><LowestSpO2>91</LowestSpO2><Desaturation>4</Desaturation><Name>SpO2 desaturation</Name><Start>18883</Start><Duration>13.8</Duration><Input>SaO2</Input></ScoredEvent><ScoredEvent><Name>Arousal ()</Name><Start>18926.3</Start><Duration>12</Duration><Input>EEG</Input></ScoredEvent><ScoredEvent><Name>Hypopnea</Name><Start>19116.1</Start><Duration>26.1</Duration><Input>ABDO RES</Input></ScoredEvent><ScoredEvent><LowestSpO2>92</LowestSpO2><Desaturation>3</Desaturation><Name>SpO2 desaturation</Name><Start>19146.1</Start><Duration>26.1</Duration><Input>SaO2</Input></ScoredEvent><ScoredEvent><Name>Arousal ()</Name><Start>19192.5</Start><Duration>4.2</Duration><Input>EEG</Input></ScoredEvent><ScoredEvent><Name>Arousal ()</Name><Start>19242.9</Start><Duration>10.7</Duration><Input>EEG</Input></ScoredEvent><ScoredEvent><Name>SpO2 artifact</Name><Start>19272.1</Start><Duration>34.1</Duration><Input>SaO2</Input></ScoredEvent><ScoredEvent><Name>Arousal ()</Name><Start>19342.7</Start><Duration>13.3</Duration><Input>EEG</Input></ScoredEvent><ScoredEvent><Name>Hypopnea</Name><Start>19451.2</Start><Duration>15.1</Duration><Input>ABDO RES</Input></ScoredEvent><ScoredEvent><Name>Hypopnea</Name><Start>19480.5</Start><Duration>22.2</Duration><Input>ABDO RES</Input></ScoredEvent><ScoredEvent><LowestSpO2>92</LowestSpO2><Desaturation>2</Desaturation><Name>SpO2 desaturation</Name><Start>19481.2</Start><Duration>15.1</Duration><Input>SaO2</Input></ScoredEvent><ScoredEvent><LowestSpO2>93</LowestSpO2><Desaturation>1</Desaturation><Name>SpO2 desaturation</Name><Start>19510.5</Start><Duration>22.2</Duration><Input>SaO2</Input></ScoredEvent><ScoredEvent><Name>Arousal ()</Name><Start>20008.5</Start><Duration>6.5</Duration><Input>EEG</Input></ScoredEvent><ScoredEvent><Name>Arousal ()</Name><Start>21412.9</Start><Duration>5.8</Duration><Input>EEG</Input></ScoredEvent><ScoredEvent><Name>Arousal ()</Name><Start>21462.2</Start><Duration>17.8</Duration><Input>EEG</Input></ScoredEvent><ScoredEvent><Name>Arousal ()</Name><Start>21513.6</Start><Duration>20.8</Duration><Input>EEG</Input></ScoredEvent><ScoredEvent><Name>Arousal ()</Name><Start>21553</Start><Duration>14.7</Duration><Input>EEG</Input></ScoredEvent><ScoredEvent><Name>SpO2 artifact</Name><Start>21583</Start><Duration>4</Duration><Input>SaO2</Input></ScoredEvent><ScoredEvent><Name>Arousal ()</Name><Start>21619.8</Start><Duration>7.4</Duration><Input>EEG</Input></ScoredEvent><ScoredEvent><Name>Arousal ()</Name><Start>21649</Start><Duration>11.7</Duration><Input>EEG</Input></ScoredEvent><ScoredEvent><Name>Arousal ()</Name><Start>21827.9</Start><Duration>6.9</Duration><Input>EEG</Input></ScoredEvent><ScoredEvent><Name>Arousal ()</Name><Start>21853.6</Start><Duration>8</Duration><Input>EEG</Input></ScoredEvent><ScoredEvent><Name>Arousal ()</Name><Start>21890.6</Start><Duration>24.4</Duration><Input>EEG</Input></ScoredEvent><ScoredEvent><Name>SpO2 artifact</Name><Start>21905</Start><Duration>7</Duration><Input>SaO2</Input></ScoredEvent><ScoredEvent><Name>SpO2 artifact</Name><Start>21987</Start><Duration>7</Duration><Input>SaO2</Input></ScoredEvent><ScoredEvent><Name>Arousal ()</Name><Start>22261.9</Start><Duration>4.7</Duration><Input>EEG</Input></ScoredEvent><ScoredEvent><Name>Arousal ()</Name><Start>22314.2</Start><Duration>4.8</Duration><Input>EEG</Input></ScoredEvent><ScoredEvent><Name>Arousal ()</Name><Start>22406.5</Start><Duration>6.2</Duration><Input>EEG</Input></ScoredEvent><ScoredEvent><Name>Arousal ()</Name><Start>22477.5</Start><Duration>7.9</Duration><Input>EEG</Input></ScoredEvent><ScoredEvent><Name>Arousal ()</Name><Start>22713.2</Start><Duration>4</Duration><Input>EEG</Input></ScoredEvent><ScoredEvent><Name>Hypopnea</Name><Start>22771</Start><Duration>15.3</Duration><Input>ABDO RES</Input></ScoredEvent><ScoredEvent><LowestSpO2>92</LowestSpO2><Desaturation>1</Desaturation><Name>SpO2 desaturation</Name><Start>22801</Start><Duration>15.3</Duration><Input>SaO2</Input></ScoredEvent><ScoredEvent><Name>Hypopnea</Name><Start>22864.1</Start><Duration>50.4</Duration><Input>ABDO RES</Input></ScoredEvent><ScoredEvent><Name>Arousal ()</Name><Start>22915.1</Start><Duration>14.4</Duration><Input>EEG</Input></ScoredEvent><ScoredEvent><Name>SpO2 artifact</Name><Start>22930</Start><Duration>3</Duration><Input>SaO2</Input></ScoredEvent><ScoredEvent><Name>Arousal ()</Name><Start>22986.6</Start><Duration>7.2</Duration><Input>EEG</Input></ScoredEvent><ScoredEvent><Name>Hypopnea</Name><Start>23002.1</Start><Duration>21.5</Duration><Input>ABDO RES</Input></ScoredEvent><ScoredEvent><LowestSpO2>93</LowestSpO2><Desaturation>2</Desaturation><Name>SpO2 desaturation</Name><Start>23032.1</Start><Duration>21.5</Duration><Input>SaO2</Input></ScoredEvent><ScoredEvent><Name>Hypopnea</Name><Start>23071.6</Start><Duration>23.3</Duration><Input>ABDO RES</Input></ScoredEvent><ScoredEvent><LowestSpO2>93</LowestSpO2><Desaturation>2</Desaturation><Name>SpO2 desaturation</Name><Start>23101.6</Start><Duration>23.3</Duration><Input>SaO2</Input></ScoredEvent><ScoredEvent><Name>Hypopnea</Name><Start>23229.3</Start><Duration>23.5</Duration><Input>ABDO RES</Input></ScoredEvent><ScoredEvent><LowestSpO2>92</LowestSpO2><Desaturation>4</Desaturation><Name>SpO2 desaturation</Name><Start>23259.3</Start><Duration>23.5</Duration><Input>SaO2</Input></ScoredEvent><ScoredEvent><Name>Hypopnea</Name><Start>23290</Start><Duration>25.4</Duration><Input>ABDO RES</Input></ScoredEvent><ScoredEvent><LowestSpO2>93</LowestSpO2><Desaturation>3</Desaturation><Name>SpO2 desaturation</Name><Start>23320</Start><Duration>25.4</Duration><Input>SaO2</Input></ScoredEvent><ScoredEvent><Name>Hypopnea</Name><Start>23332.2</Start><Duration>12.6</Duration><Input>ABDO RES</Input></ScoredEvent><ScoredEvent><LowestSpO2>94</LowestSpO2><Desaturation>0</Desaturation><Name>SpO2 desaturation</Name><Start>23362.2</Start><Duration>12.6</Duration><Input>SaO2</Input></ScoredEvent><ScoredEvent><Name>Hypopnea</Name><Start>23366.3</Start><Duration>21.2</Duration><Input>ABDO RES</Input></ScoredEvent><ScoredEvent><LowestSpO2>93</LowestSpO2><Desaturation>3</Desaturation><Name>SpO2 desaturation</Name><Start>23396.3</Start><Duration>21.2</Duration><Input>SaO2</Input></ScoredEvent><ScoredEvent><Name>Hypopnea</Name><Start>23397.3</Start><Duration>19.5</Duration><Input>ABDO RES</Input></ScoredEvent><ScoredEvent><LowestSpO2>92</LowestSpO2><Desaturation>4</Desaturation><Name>SpO2 desaturation</Name><Start>23427.3</Start><Duration>19.5</Duration><Input>SaO2</Input></ScoredEvent><ScoredEvent><Name>Hypopnea</Name><Start>23439.2</Start><Duration>11.5</Duration><Input>ABDO RES</Input></ScoredEvent><ScoredEvent><LowestSpO2>94</LowestSpO2><Desaturation>1</Desaturation><Name>SpO2 desaturation</Name><Start>23469.2</Start><Duration>11.5</Duration><Input>SaO2</Input></ScoredEvent><ScoredEvent><Name>Hypopnea</Name><Start>23481</Start><Duration>12.5</Duration><Input>ABDO RES</Input></ScoredEvent><ScoredEvent><Name>Arousal ()</Name><Start>23502.6</Start><Duration>6.5</Duration><Input>EEG</Input></ScoredEvent><ScoredEvent><LowestSpO2>95</LowestSpO2><Desaturation>0</Desaturation><Name>SpO2 desaturation</Name><Start>23511</Start><Duration>12.5</Duration><Input>SaO2</Input></ScoredEvent><ScoredEvent><Name>Arousal ()</Name><Start>23546.8</Start><Duration>5</Duration><Input>EEG</Input></ScoredEvent><ScoredEvent><Name>Hypopnea</Name><Start>23569.8</Start><Duration>12.6</Duration><Input>ABDO RES</Input></ScoredEvent><ScoredEvent><Name>Arousal ()</Name><Start>23591.5</Start><Duration>5.9</Duration><Input>EEG</Input></ScoredEvent><ScoredEvent><LowestSpO2>94</LowestSpO2><Desaturation>2</Desaturation><Name>SpO2 desaturation</Name><Start>23599.8</Start><Duration>12.6</Duration><Input>SaO2</Input></ScoredEvent><ScoredEvent><Name>Arousal ()</Name><Start>23667.8</Start><Duration>4.1</Duration><Input>EEG</Input></ScoredEvent><ScoredEvent><Name>Arousal ()</Name><Start>23764</Start><Duration>5.1</Duration><Input>EEG</Input></ScoredEvent><ScoredEvent><Name>Hypopnea</Name><Start>23916.4</Start><Duration>19.9</Duration><Input>ABDO RES</Input></ScoredEvent><ScoredEvent><LowestSpO2>92</LowestSpO2><Desaturation>3</Desaturation><Name>SpO2 desaturation</Name><Start>23946.4</Start><Duration>19.9</Duration><Input>SaO2</Input></ScoredEvent><ScoredEvent><Name>Arousal ()</Name><Start>23955.9</Start><Duration>8.1</Duration><Input>EEG</Input></ScoredEvent><ScoredEvent><Name>Arousal ()</Name><Start>23977.2</Start><Duration>8.5</Duration><Input>EEG</Input></ScoredEvent><ScoredEvent><Name>Hypopnea</Name><Start>24047.7</Start><Duration>15.1</Duration><Input>ABDO RES</Input></ScoredEvent><ScoredEvent><LowestSpO2>94</LowestSpO2><Desaturation>1</Desaturation><Name>SpO2 desaturation</Name><Start>24077.7</Start><Duration>15.1</Duration><Input>SaO2</Input></ScoredEvent><ScoredEvent><Name>Hypopnea</Name><Start>24096.8</Start><Duration>13.8</Duration><Input>ABDO RES</Input></ScoredEvent><ScoredEvent><Name>Hypopnea</Name><Start>24125.1</Start><Duration>17.4</Duration><Input>ABDO RES</Input></ScoredEvent><ScoredEvent><LowestSpO2>92</LowestSpO2><Desaturation>2</Desaturation><Name>SpO2 desaturation</Name><Start>24126.8</Start><Duration>13.8</Duration><Input>SaO2</Input></ScoredEvent><ScoredEvent><Name>Arousal ()</Name><Start>24145.3</Start><Duration>15</Duration><Input>EEG</Input></ScoredEvent><ScoredEvent><LowestSpO2>92</LowestSpO2><Desaturation>1</Desaturation><Name>SpO2 desaturation</Name><Start>24155.1</Start><Duration>17.4</Duration><Input>SaO2</Input></ScoredEvent><ScoredEvent><Name>Hypopnea</Name><Start>24248.4</Start><Duration>13.3</Duration><Input>ABDO RES</Input></ScoredEvent><ScoredEvent><LowestSpO2>95</LowestSpO2><Desaturation>1</Desaturation><Name>SpO2 desaturation</Name><Start>24278.4</Start><Duration>13.3</Duration><Input>SaO2</Input></ScoredEvent><ScoredEvent><Name>Arousal ()</Name><Start>24389.2</Start><Duration>12</Duration><Input>EEG</Input></ScoredEvent><ScoredEvent><Name>Arousal ()</Name><Start>24551.9</Start><Duration>18.1</Duration><Input>EEG</Input></ScoredEvent><ScoredEvent><Name>Arousal ()</Name><Start>24624.9</Start><Duration>5.3</Duration><Input>EEG</Input></ScoredEvent><ScoredEvent><Name>Arousal ()</Name><Start>25469.9</Start><Duration>4.5</Duration><Input>EEG</Input></ScoredEvent><ScoredEvent><Name>Arousal ()</Name><Start>25653.7</Start><Duration>18.9</Duration><Input>EEG</Input></ScoredEvent><ScoredEvent><Name>SpO2 artifact</Name><Start>25672</Start><Duration>4</Duration><Input>SaO2</Input></ScoredEvent><ScoredEvent><Name>Arousal ()</Name><Start>25722.5</Start><Duration>5.5</Duration><Input>EEG</Input></ScoredEvent><ScoredEvent><Name>Arousal ()</Name><Start>25793.6</Start><Duration>3.7</Duration><Input>EEG</Input></ScoredEvent><ScoredEvent><Name>Arousal ()</Name><Start>26372.7</Start><Duration>4.9</Duration><Input>EEG</Input></ScoredEvent><ScoredEvent><Name>Arousal ()</Name><Start>26774.2</Start><Duration>11.3</Duration><Input>EEG</Input></ScoredEvent><ScoredEvent><Name>Arousal ()</Name><Start>26939.5</Start><Duration>15.5</Duration><Input>EEG</Input></ScoredEvent><ScoredEvent><Name>SpO2 artifact</Name><Start>26964</Start><Duration>4</Duration><Input>SaO2</Input></ScoredEvent><ScoredEvent><Name>Arousal ()</Name><Start>27053.6</Start><Duration>20.2</Duration><Input>EEG</Input></ScoredEvent><ScoredEvent><Name>Arousal ()</Name><Start>27102.9</Start><Duration>6.7</Duration><Input>EEG</Input></ScoredEvent><ScoredEvent><Name>Arousal ()</Name><Start>27144.8</Start><Duration>11.5</Duration><Input>EEG</Input></ScoredEvent><ScoredEvent><Name>Arousal ()</Name><Start>27174.3</Start><Duration>7.6</Duration><Input>EEG</Input></ScoredEvent><ScoredEvent><Name>Arousal ()</Name><Start>27210.9</Start><Duration>10.8</Duration><Input>EEG</Input></ScoredEvent><ScoredEvent><Name>Arousal ()</Name><Start>27245</Start><Duration>4.3</Duration><Input>EEG</Input></ScoredEvent><ScoredEvent><Name>SpO2 artifact</Name><Start>27278</Start><Duration>3</Duration><Input>SaO2</Input></ScoredEvent><ScoredEvent><Name>Arousal ()</Name><Start>27372.2</Start><Duration>17.8</Duration><Input>EEG</Input></ScoredEvent><ScoredEvent><Name>Arousal ()</Name><Start>27451.2</Start><Duration>28.8</Duration><Input>EEG</Input></ScoredEvent><ScoredEvent><Name>Arousal ()</Name><Start>27509.7</Start><Duration>5.2</Duration><Input>EEG</Input></ScoredEvent><ScoredEvent><Name>Arousal ()</Name><Start>27563.4</Start><Duration>7.4</Duration><Input>EEG</Input></ScoredEvent><ScoredEvent><Name>Arousal ()</Name><Start>27599.6</Start><Duration>6.5</Duration><Input>EEG</Input></ScoredEvent><ScoredEvent><Name>Arousal ()</Name><Start>27629.9</Start><Duration>4.2</Duration><Input>EEG</Input></ScoredEvent><ScoredEvent><Name>Arousal ()</Name><Start>27876.7</Start><Duration>7.4</Duration><Input>EEG</Input></ScoredEvent><ScoredEvent><Name>Arousal ()</Name><Start>27935.7</Start><Duration>5.4</Duration><Input>EEG</Input></ScoredEvent><ScoredEvent><Name>Arousal ()</Name><Start>27993</Start><Duration>3.9</Duration><Input>EEG</Input></ScoredEvent><ScoredEvent><Name>Hypopnea</Name><Start>28007.7</Start><Duration>24.5</Duration><Input>ABDO RES</Input></ScoredEvent><ScoredEvent><Name>Arousal ()</Name><Start>28035.1</Start><Duration>5.4</Duration><Input>EEG</Input></ScoredEvent><ScoredEvent><LowestSpO2>88</LowestSpO2><Desaturation>5</Desaturation><Name>SpO2 desaturation</Name><Start>28037.7</Start><Duration>24.5</Duration><Input>SaO2</Input></ScoredEvent><ScoredEvent><Name>Hypopnea</Name><Start>28086</Start><Duration>18.9</Duration><Input>ABDO RES</Input></ScoredEvent><ScoredEvent><Name>Arousal ()</Name><Start>28103.8</Start><Duration>16.8</Duration><Input>EEG</Input></ScoredEvent><ScoredEvent><LowestSpO2>90</LowestSpO2><Desaturation>3</Desaturation><Name>SpO2 desaturation</Name><Start>28116</Start><Duration>18.9</Duration><Input>SaO2</Input></ScoredEvent><ScoredEvent><Name>Hypopnea</Name><Start>28161.5</Start><Duration>14.4</Duration><Input>ABDO RES</Input></ScoredEvent><ScoredEvent><LowestSpO2>90</LowestSpO2><Desaturation>3</Desaturation><Name>SpO2 desaturation</Name><Start>28191.5</Start><Duration>14.4</Duration><Input>SaO2</Input></ScoredEvent><ScoredEvent><Name>Hypopnea</Name><Start>28254.4</Start><Duration>16.6</Duration><Input>ABDO RES</Input></ScoredEvent><ScoredEvent><LowestSpO2>90</LowestSpO2><Desaturation>2</Desaturation><Name>SpO2 desaturation</Name><Start>28284.4</Start><Duration>16.6</Duration><Input>SaO2</Input></ScoredEvent><ScoredEvent><Name>Hypopnea</Name><Start>28348.6</Start><Duration>19.2</Duration><Input>ABDO RES</Input></ScoredEvent><ScoredEvent><LowestSpO2>91</LowestSpO2><Desaturation>2</Desaturation><Name>SpO2 desaturation</Name><Start>28378.6</Start><Duration>19.2</Duration><Input>SaO2</Input></ScoredEvent><ScoredEvent><Name>Hypopnea</Name><Start>28644.3</Start><Duration>20.2</Duration><Input>ABDO RES</Input></ScoredEvent><ScoredEvent><LowestSpO2>91</LowestSpO2><Desaturation>3</Desaturation><Name>SpO2 desaturation</Name><Start>28674.3</Start><Duration>20.2</Duration><Input>SaO2</Input></ScoredEvent><ScoredEvent><Name>Hypopnea</Name><Start>28680.3</Start><Duration>16.7</Duration><Input>ABDO RES</Input></ScoredEvent><ScoredEvent><LowestSpO2>91</LowestSpO2><Desaturation>2</Desaturation><Name>SpO2 desaturation</Name><Start>28710.3</Start><Duration>16.7</Duration><Input>SaO2</Input></ScoredEvent><ScoredEvent><Name>Hypopnea</Name><Start>28727</Start><Duration>16.9</Duration><Input>ABDO RES</Input></ScoredEvent><ScoredEvent><LowestSpO2>92</LowestSpO2><Desaturation>1</Desaturation><Name>SpO2 desaturation</Name><Start>28757</Start><Duration>16.9</Duration><Input>SaO2</Input></ScoredEvent><ScoredEvent><Name>Hypopnea</Name><Start>28901.2</Start><Duration>14.6</Duration><Input>ABDO RES</Input></ScoredEvent><ScoredEvent><LowestSpO2>89</LowestSpO2><Desaturation>4</Desaturation><Name>SpO2 desaturation</Name><Start>28931.2</Start><Duration>14.6</Duration><Input>SaO2</Input></ScoredEvent><ScoredEvent><Name>Arousal ()</Name><Start>28939.2</Start><Duration>10.1</Duration><Input>EEG</Input></ScoredEvent><ScoredEvent><Name>Hypopnea</Name><Start>28965.5</Start><Duration>31.5</Duration><Input>ABDO RES</Input></ScoredEvent><ScoredEvent><LowestSpO2>90</LowestSpO2><Desaturation>4</Desaturation><Name>SpO2 desaturation</Name><Start>28995.5</Start><Duration>31.5</Duration><Input>SaO2</Input></ScoredEvent><ScoredEvent><Name>Hypopnea</Name><Start>29084.5</Start><Duration>19.5</Duration><Input>ABDO RES</Input></ScoredEvent><ScoredEvent><LowestSpO2>89</LowestSpO2><Desaturation>4</Desaturation><Name>SpO2 desaturation</Name><Start>29114.5</Start><Duration>19.5</Duration><Input>SaO2</Input></ScoredEvent><ScoredEvent><Name>Hypopnea</Name><Start>29218.2</Start><Duration>24.3</Duration><Input>ABDO RES</Input></ScoredEvent><ScoredEvent><LowestSpO2>90</LowestSpO2><Desaturation>2</Desaturation><Name>SpO2 desaturation</Name><Start>29248.2</Start><Duration>24.3</Duration><Input>SaO2</Input></ScoredEvent><ScoredEvent><Name>Hypopnea</Name><Start>29284.2</Start><Duration>15.3</Duration><Input>ABDO RES</Input></ScoredEvent><ScoredEvent><Name>Hypopnea</Name><Start>29379.9</Start><Duration>17.7</Duration><Input>ABDO RES</Input></ScoredEvent><ScoredEvent><Name>Hypopnea</Name><Start>29417.5</Start><Duration>36.1</Duration><Input>ABDO RES</Input></ScoredEvent><ScoredEvent><Name>Arousal ()</Name><Start>29455.9</Start><Duration>15.3</Duration><Input>EEG</Input></ScoredEvent><ScoredEvent><Name>Hypopnea</Name><Start>29534.3</Start><Duration>14.3</Duration><Input>ABDO RES</Input></ScoredEvent><ScoredEvent><Name>Arousal ()</Name><Start>29553.1</Start><Duration>4.4</Duration><Input>EEG</Input></ScoredEvent><ScoredEvent><Name>Hypopnea</Name><Start>29628.2</Start><Duration>25.3</Duration><Input>ABDO RES</Input></ScoredEvent><ScoredEvent><Name>Arousal ()</Name><Start>29697.1</Start><Duration>10.5</Duration><Input>EEG</Input></ScoredEvent><ScoredEvent><Name>Hypopnea</Name><Start>29821.2</Start><Duration>14.9</Duration><Input>ABDO RES</Input></ScoredEvent><ScoredEvent><Name>Hypopnea</Name><Start>29987.6</Start><Duration>20.5</Duration><Input>ABDO RES</Input></ScoredEvent><ScoredEvent><Name>Hypopnea</Name><Start>30053.6</Start><Duration>17.6</Duration><Input>ABDO RES</Input></ScoredEvent><ScoredEvent><Name>Arousal ()</Name><Start>30081.8</Start><Duration>22.3</Duration><Input>EEG</Input></ScoredEvent><ScoredEvent><Name>Hypopnea</Name><Start>30193.6</Start><Duration>16.4</Duration><Input>ABDO RES</Input></ScoredEvent><ScoredEvent><Name>Arousal ()</Name><Start>30254.7</Start><Duration>11.6</Duration><Input>EEG</Input></ScoredEvent><ScoredEvent><Name>Arousal ()</Name><Start>30323.2</Start><Duration>7.1</Duration><Input>EEG</Input></ScoredEvent><ScoredEvent><Name>Arousal ()</Name><Start>30384</Start><Duration>9</Duration><Input>EEG</Input></ScoredEvent><ScoredEvent><Name>Arousal ()</Name><Start>30485.5</Start><Duration>5.7</Duration><Input>EEG</Input></ScoredEvent><ScoredEvent><Name>Hypopnea</Name><Start>30601.2</Start><Duration>18.1</Duration><Input>ABDO RES</Input></ScoredEvent><ScoredEvent><Name>Arousal ()</Name><Start>30797.2</Start><Duration>27.8</Duration><Input>EEG</Input></ScoredEvent><ScoredEvent><Name>Arousal ()</Name><Start>30927.1</Start><Duration>7.2</Duration><Input>EEG</Input></ScoredEvent><ScoredEvent><Name>Arousal ()</Name><Start>31846.3</Start><Duration>13.7</Duration><Input>EEG</Input></ScoredEvent><ScoredEvent><Name>Arousal ()</Name><Start>31874</Start><Duration>11.7</Duration><Input>EEG</Input></ScoredEvent><ScoredEvent><Name>Arousal ()</Name><Start>31974.4</Start><Duration>11</Duration><Input>EEG</Input></ScoredEvent><ScoredEvent><Name>Arousal ()</Name><Start>32061.3</Start><Duration>10.3</Duration><Input>EEG</Input></ScoredEvent><ScoredEvent><Name>Arousal ()</Name><Start>32088.5</Start><Duration>5.5</Duration><Input>EEG</Input></ScoredEvent><ScoredEvent><Name>Arousal ()</Name><Start>32107.6</Start><Duration>9.5</Duration><Input>EEG</Input></ScoredEvent><ScoredEvent><Name>Arousal ()</Name><Start>32153.7</Start><Duration>14.1</Duration><Input>EEG</Input></ScoredEvent><ScoredEvent><Name>Arousal ()</Name><Start>32245.8</Start><Duration>19.2</Duration><Input>EEG</Input></ScoredEvent><ScoredEvent><Name>SpO2 artifact</Name><Start>32265</Start><Duration>6</Duration><Input>SaO2</Input></ScoredEvent><ScoredEvent><Name>Arousal ()</Name><Start>32324.5</Start><Duration>5.7</Duration><Input>EEG</Input></ScoredEvent><ScoredEvent><Name>Arousal ()</Name><Start>32353.3</Start><Duration>7.6</Duration><Input>EEG</Input></ScoredEvent><ScoredEvent><Name>Arousal ()</Name><Start>32394.4</Start><Duration>4.1</Duration><Input>EEG</Input></ScoredEvent><ScoredEvent><Name>Arousal ()</Name><Start>32433.9</Start><Duration>11.7</Duration><Input>EEG</Input></ScoredEvent><ScoredEvent><Name>Arousal ()</Name><Start>32564.8</Start><Duration>7.7</Duration><Input>EEG</Input></ScoredEvent><ScoredEvent><Name>Arousal ()</Name><Start>32675.8</Start><Duration>7</Duration><Input>EEG</Input></ScoredEvent><ScoredEvent><Name>Hypopnea</Name><Start>32722.1</Start><Duration>23.3</Duration><Input>ABDO RES</Input></ScoredEvent><ScoredEvent><Name>Arousal ()</Name><Start>32742.6</Start><Duration>4.3</Duration><Input>EEG</Input></ScoredEvent><ScoredEvent><Name>Hypopnea</Name><Start>32778.2</Start><Duration>18.9</Duration><Input>ABDO RES</Input></ScoredEvent><ScoredEvent><Name>Arousal ()</Name><Start>32964.3</Start><Duration>16.1</Duration><Input>EEG</Input></ScoredEvent><ScoredEvent><Name>Arousal ()</Name><Start>33039.1</Start><Duration>9.1</Duration><Input>EEG</Input></ScoredEvent><ScoredEvent><Name>Arousal ()</Name><Start>33097</Start><Duration>3.8</Duration><Input>EEG</Input></ScoredEvent><ScoredEvent><Name>Arousal ()</Name><Start>33279.1</Start><Duration>20.8</Duration><Input>EEG</Input></ScoredEvent><ScoredEvent><Name>Arousal ()</Name><Start>33345.9</Start><Duration>12.1</Duration><Input>EEG</Input></ScoredEvent><ScoredEvent><Name>Arousal ()</Name><Start>33428.3</Start><Duration>5.3</Duration><Input>EEG</Input></ScoredEvent><ScoredEvent><Name>Arousal ()</Name><Start>33542.4</Start><Duration>5.8</Duration><Input>EEG</Input></ScoredEvent><ScoredEvent><Name>Arousal ()</Name><Start>33636.8</Start><Duration>3.9</Duration><Input>EEG</Input></ScoredEvent><ScoredEvent><Name>Arousal ()</Name><Start>33746.5</Start><Duration>6.7</Duration><Input>EEG</Input></ScoredEvent><ScoredEvent><Name>Arousal ()</Name><Start>34370.1</Start><Duration>3.6</Duration><Input>EEG</Input></ScoredEvent><ScoredEvent><Name>Arousal ()</Name><Start>34501.7</Start><Duration>5.8</Duration><Input>EEG</Input></ScoredEvent><ScoredEvent><Name>Arousal ()</Name><Start>34657.8</Start><Duration>20.7</Duration><Input>EEG</Input></ScoredEvent><ScoredEvent><Name>SpO2 artifact</Name><Start>34678</Start><Duration>6</Duration><Input>SaO2</Input></ScoredEvent><ScoredEvent><Name>Arousal ()</Name><Start>34753.2</Start><Duration>16.8</Duration><Input>EEG</Input></ScoredEvent><ScoredEvent><Name>Arousal ()</Name><Start>34861.5</Start><Duration>28.5</Duration><Input>EEG</Input></ScoredEvent><ScoredEvent><Name>SpO2 artifact</Name><Start>35927</Start><Duration>4</Duration><Input>SaO2</Input></ScoredEvent><ScoredEvent><Name>SpO2 artifact</Name><Start>36748</Start><Duration>6</Duration><Input>SaO2</Input></ScoredEvent><ScoredEvent><Name>SpO2 artifact</Name><Start>37986</Start><Duration>4</Duration><Input>SaO2</Input></ScoredEvent><ScoredEvent><Name>SpO2 artifact</Name><Start>38014</Start><Duration>4</Duration><Input>SaO2</Input></ScoredEvent><ScoredEvent><Name>SpO2 artifact</Name><Start>38114</Start><Duration>19</Duration><Input>SaO2</Input></ScoredEvent><ScoredEvent><Name>SpO2 artifact</Name><Start>38157</Start><Duration>6</Duration><Input>SaO2</Input></ScoredEvent><ScoredEvent><Name>SpO2 artifact</Name><Start>38173</Start><Duration>4</Duration><Input>SaO2</Input></ScoredEvent><ScoredEvent><Name>SpO2 artifact</Name><Start>38197</Start><Duration>12</Duration><Input>SaO2</Input></ScoredEvent><ScoredEvent><Name>SpO2 artifact</Name><Start>39478</Start><Duration>7</Duration><Input>SaO2</Input></ScoredEvent><ScoredEvent><Name>SpO2 artifact</Name><Start>39712</Start><Duration>4</Duration><Input>SaO2</Input></ScoredEvent></ScoredEvents><SleepStages><SleepStage>0</SleepStage><SleepStage>0</SleepStage><SleepStage>0</SleepStage><SleepStage>0</SleepStage><SleepStage>0</SleepStage><SleepStage>0</SleepStage><SleepStage>0</SleepStage><SleepStage>0</SleepStage><SleepStage>0</SleepStage><SleepStage>0</SleepStage><SleepStage>0</SleepStage><SleepStage>0</SleepStage><SleepStage>0</SleepStage><SleepStage>0</SleepStage><SleepStage>0</SleepStage><SleepStage>0</SleepStage><SleepStage>0</SleepStage><SleepStage>0</SleepStage><SleepStage>0</SleepStage><SleepStage>0</SleepStage><SleepStage>0</SleepStage><SleepStage>0</SleepStage><SleepStage>0</SleepStage><SleepStage>0</SleepStage><SleepStage>0</SleepStage><SleepStage>0</SleepStage><SleepStage>0</SleepStage><SleepStage>0</SleepStage><SleepStage>0</SleepStage><SleepStage>0</SleepStage><SleepStage>0</SleepStage><SleepStage>0</SleepStage><SleepStage>0</SleepStage><SleepStage>0</SleepStage><SleepStage>0</SleepStage><SleepStage>0</SleepStage><SleepStage>0</SleepStage><SleepStage>0</SleepStage><SleepStage>0</SleepStage><SleepStage>0</SleepStage><SleepStage>0</SleepStage><SleepStage>0</SleepStage><SleepStage>0</SleepStage><SleepStage>0</SleepStage><SleepStage>0</SleepStage><SleepStage>0</SleepStage><SleepStage>0</SleepStage><SleepStage>0</SleepStage><SleepStage>0</SleepStage><SleepStage>0</SleepStage><SleepStage>0</SleepStage><SleepStage>0</SleepStage><SleepStage>0</SleepStage><SleepStage>0</SleepStage><SleepStage>0</SleepStage><SleepStage>0</SleepStage><SleepStage>0</SleepStage><SleepStage>0</SleepStage><SleepStage>0</SleepStage><SleepStage>0</SleepStage><SleepStage>0</SleepStage><SleepStage>0</SleepStage><SleepStage>0</SleepStage><SleepStage>0</SleepStage><SleepStage>0</SleepStage><SleepStage>0</SleepStage><SleepStage>0</SleepStage><SleepStage>0</SleepStage><SleepStage>0</SleepStage><SleepStage>0</SleepStage><SleepStage>0</SleepStage><SleepStage>0</SleepStage><SleepStage>0</SleepStage><SleepStage>0</SleepStage><SleepStage>0</SleepStage><SleepStage>0</SleepStage><SleepStage>0</SleepStage><SleepStage>0</SleepStage><SleepStage>0</SleepStage><SleepStage>0</SleepStage><SleepStage>0</SleepStage><SleepStage>0</SleepStage><SleepStage>0</SleepStage><SleepStage>0</SleepStage><SleepStage>0</SleepStage><SleepStage>0</SleepStage><SleepStage>0</SleepStage><SleepStage>0</SleepStage><SleepStage>0</SleepStage><SleepStage>0</SleepStage><SleepStage>0</SleepStage><SleepStage>0</SleepStage><SleepStage>0</SleepStage><SleepStage>0</SleepStage><SleepStage>0</SleepStage><SleepStage>0</SleepStage><SleepStage>0</SleepStage><SleepStage>0</SleepStage><SleepStage>0</SleepStage><SleepStage>0</SleepStage><SleepStage>0</SleepStage><SleepStage>0</SleepStage><SleepStage>0</SleepStage><SleepStage>0</SleepStage><SleepStage>0</SleepStage><SleepStage>0</SleepStage><SleepStage>0</SleepStage><SleepStage>0</SleepStage><SleepStage>0</SleepStage><SleepStage>0</SleepStage><SleepStage>0</SleepStage><SleepStage>0</SleepStage><SleepStage>0</SleepStage><SleepStage>0</SleepStage><SleepStage>0</SleepStage><SleepStage>0</SleepStage><SleepStage>0</SleepStage><SleepStage>0</SleepStage><SleepStage>0</SleepStage><SleepStage>0</SleepStage><SleepStage>0</SleepStage><SleepStage>0</SleepStage><SleepStage>0</SleepStage><SleepStage>0</SleepStage><SleepStage>0</SleepStage><SleepStage>0</SleepStage><SleepStage>0</SleepStage><SleepStage>0</SleepStage><SleepStage>0</SleepStage><SleepStage>0</SleepStage><SleepStage>0</SleepStage><SleepStage>0</SleepStage><SleepStage>0</SleepStage><SleepStage>0</SleepStage><SleepStage>0</SleepStage><SleepStage>0</SleepStage><SleepStage>0</SleepStage><SleepStage>0</SleepStage><SleepStage>0</SleepStage><SleepStage>0</SleepStage><SleepStage>0</SleepStage><SleepStage>0</SleepStage><SleepStage>0</SleepStage><SleepStage>0</SleepStage><SleepStage>0</SleepStage><SleepStage>0</SleepStage><SleepStage>0</SleepStage><SleepStage>0</SleepStage><SleepStage>0</SleepStage><SleepStage>0</SleepStage><SleepStage>0</SleepStage><SleepStage>0</SleepStage><SleepStage>0</SleepStage><SleepStage>0</SleepStage><SleepStage>0</SleepStage><SleepStage>0</SleepStage><SleepStage>0</SleepStage><SleepStage>0</SleepStage><SleepStage>0</SleepStage><SleepStage>0</SleepStage><SleepStage>0</SleepStage><SleepStage>0</SleepStage><SleepStage>0</SleepStage><SleepStage>0</SleepStage><SleepStage>0</SleepStage><SleepStage>0</SleepStage><SleepStage>0</SleepStage><SleepStage>0</SleepStage><SleepStage>0</SleepStage><SleepStage>0</SleepStage><SleepStage>0</SleepStage><SleepStage>0</SleepStage><SleepStage>0</SleepStage><SleepStage>0</SleepStage><SleepStage>0</SleepStage><SleepStage>0</SleepStage><SleepStage>0</SleepStage><SleepStage>0</SleepStage><SleepStage>0</SleepStage><SleepStage>0</SleepStage><SleepStage>0</SleepStage><SleepStage>0</SleepStage><SleepStage>0</SleepStage><SleepStage>0</SleepStage><SleepStage>0</SleepStage><SleepStage>0</SleepStage><SleepStage>0</SleepStage><SleepStage>0</SleepStage><SleepStage>0</SleepStage><SleepStage>0</SleepStage><SleepStage>0</SleepStage><SleepStage>0</SleepStage><SleepStage>0</SleepStage><SleepStage>0</SleepStage><SleepStage>0</SleepStage><SleepStage>0</SleepStage><SleepStage>0</SleepStage><SleepStage>0</SleepStage><SleepStage>0</SleepStage><SleepStage>0</SleepStage><SleepStage>0</SleepStage><SleepStage>0</SleepStage><SleepStage>0</SleepStage><SleepStage>0</SleepStage><SleepStage>0</SleepStage><SleepStage>0</SleepStage><SleepStage>0</SleepStage><SleepStage>0</SleepStage><SleepStage>0</SleepStage><SleepStage>0</SleepStage><SleepStage>0</SleepStage><SleepStage>0</SleepStage><SleepStage>0</SleepStage><SleepStage>0</SleepStage><SleepStage>0</SleepStage><SleepStage>0</SleepStage><SleepStage>0</SleepStage><SleepStage>0</SleepStage><SleepStage>0</SleepStage><SleepStage>0</SleepStage><SleepStage>0</SleepStage><SleepStage>0</SleepStage><SleepStage>0</SleepStage><SleepStage>0</SleepStage><SleepStage>0</SleepStage><SleepStage>0</SleepStage><SleepStage>0</SleepStage><SleepStage>0</SleepStage><SleepStage>0</SleepStage><SleepStage>0</SleepStage><SleepStage>0</SleepStage><SleepStage>0</SleepStage><SleepStage>0</SleepStage><SleepStage>0</SleepStage><SleepStage>0</SleepStage><SleepStage>0</SleepStage><SleepStage>0</SleepStage><SleepStage>0</SleepStage><SleepStage>0</SleepStage><SleepStage>0</SleepStage><SleepStage>0</SleepStage><SleepStage>0</SleepStage><SleepStage>0</SleepStage><SleepStage>0</SleepStage><SleepStage>0</SleepStage><SleepStage>0</SleepStage><SleepStage>0</SleepStage><SleepStage>0</SleepStage><SleepStage>0</SleepStage><SleepStage>0</SleepStage><SleepStage>0</SleepStage><SleepStage>0</SleepStage><SleepStage>0</SleepStage><SleepStage>0</SleepStage><SleepStage>0</SleepStage><SleepStage>0</SleepStage><SleepStage>0</SleepStage><SleepStage>0</SleepStage><SleepStage>0</SleepStage><SleepStage>0</SleepStage><SleepStage>0</SleepStage><SleepStage>0</SleepStage><SleepStage>0</SleepStage><SleepStage>0</SleepStage><SleepStage>0</SleepStage><SleepStage>0</SleepStage><SleepStage>0</SleepStage><SleepStage>0</SleepStage><SleepStage>0</SleepStage><SleepStage>0</SleepStage><SleepStage>0</SleepStage><SleepStage>0</SleepStage><SleepStage>0</SleepStage><SleepStage>0</SleepStage><SleepStage>0</SleepStage><SleepStage>0</SleepStage><SleepStage>0</SleepStage><SleepStage>0</SleepStage><SleepStage>0</SleepStage><SleepStage>0</SleepStage><SleepStage>0</SleepStage><SleepStage>0</SleepStage><SleepStage>0</SleepStage><SleepStage>0</SleepStage><SleepStage>0</SleepStage><SleepStage>0</SleepStage><SleepStage>0</SleepStage><SleepStage>0</SleepStage><SleepStage>0</SleepStage><SleepStage>0</SleepStage><SleepStage>0</SleepStage><SleepStage>0</SleepStage><SleepStage>0</SleepStage><SleepStage>0</SleepStage><SleepStage>0</SleepStage><SleepStage>0</SleepStage><SleepStage>0</SleepStage><SleepStage>0</SleepStage><SleepStage>0</SleepStage><SleepStage>0</SleepStage><SleepStage>0</SleepStage><SleepStage>0</SleepStage><SleepStage>0</SleepStage><SleepStage>0</SleepStage><SleepStage>0</SleepStage><SleepStage>0</SleepStage><SleepStage>0</SleepStage><SleepStage>0</SleepStage><SleepStage>0</SleepStage><SleepStage>0</SleepStage><SleepStage>0</SleepStage><SleepStage>0</SleepStage><SleepStage>0</SleepStage><SleepStage>0</SleepStage><SleepStage>0</SleepStage><SleepStage>0</SleepStage><SleepStage>0</SleepStage><SleepStage>0</SleepStage><SleepStage>0</SleepStage><SleepStage>0</SleepStage><SleepStage>0</SleepStage><SleepStage>0</SleepStage><SleepStage>0</SleepStage><SleepStage>0</SleepStage><SleepStage>0</SleepStage><SleepStage>0</SleepStage><SleepStage>0</SleepStage><SleepStage>0</SleepStage><SleepStage>0</SleepStage><SleepStage>0</SleepStage><SleepStage>0</SleepStage><SleepStage>0</SleepStage><SleepStage>0</SleepStage><SleepStage>0</SleepStage><SleepStage>0</SleepStage><SleepStage>0</SleepStage><SleepStage>0</SleepStage><SleepStage>0</SleepStage><SleepStage>0</SleepStage><SleepStage>0</SleepStage><SleepStage>0</SleepStage><SleepStage>0</SleepStage><SleepStage>0</SleepStage><SleepStage>0</SleepStage><SleepStage>0</SleepStage><SleepStage>0</SleepStage><SleepStage>0</SleepStage><SleepStage>1</SleepStage><SleepStage>1</SleepStage><SleepStage>1</SleepStage><SleepStage>1</SleepStage><SleepStage>2</SleepStage><SleepStage>0</SleepStage><SleepStage>1</SleepStage><SleepStage>1</SleepStage><SleepStage>1</SleepStage><SleepStage>1</SleepStage><SleepStage>0</SleepStage><SleepStage>1</SleepStage><SleepStage>1</SleepStage><SleepStage>2</SleepStage><SleepStage>2</SleepStage><SleepStage>2</SleepStage><SleepStage>2</SleepStage><SleepStage>2</SleepStage><SleepStage>2</SleepStage><SleepStage>2</SleepStage><SleepStage>2</SleepStage><SleepStage>2</SleepStage><SleepStage>2</SleepStage><SleepStage>2</SleepStage><SleepStage>2</SleepStage><SleepStage>2</SleepStage><SleepStage>2</SleepStage><SleepStage>2</SleepStage><SleepStage>2</SleepStage><SleepStage>2</SleepStage><SleepStage>2</SleepStage><SleepStage>3</SleepStage><SleepStage>2</SleepStage><SleepStage>3</SleepStage><SleepStage>3</SleepStage><SleepStage>2</SleepStage><SleepStage>2</SleepStage><SleepStage>3</SleepStage><SleepStage>3</SleepStage><SleepStage>3</SleepStage><SleepStage>3</SleepStage><SleepStage>2</SleepStage><SleepStage>3</SleepStage><SleepStage>3</SleepStage><SleepStage>3</SleepStage><SleepStage>2</SleepStage><SleepStage>3</SleepStage><SleepStage>3</SleepStage><SleepStage>3</SleepStage><SleepStage>3</SleepStage><SleepStage>3</SleepStage><SleepStage>3</SleepStage><SleepStage>3</SleepStage><SleepStage>3</SleepStage><SleepStage>2</SleepStage><SleepStage>3</SleepStage><SleepStage>3</SleepStage><SleepStage>3</SleepStage><SleepStage>3</SleepStage><SleepStage>3</SleepStage><SleepStage>3</SleepStage><SleepStage>3</SleepStage><SleepStage>3</SleepStage><SleepStage>3</SleepStage><SleepStage>3</SleepStage><SleepStage>3</SleepStage><SleepStage>2</SleepStage><SleepStage>3</SleepStage><SleepStage>3</SleepStage><SleepStage>3</SleepStage><SleepStage>3</SleepStage><SleepStage>3</SleepStage><SleepStage>2</SleepStage><SleepStage>2</SleepStage><SleepStage>3</SleepStage><SleepStage>3</SleepStage><SleepStage>3</SleepStage><SleepStage>3</SleepStage><SleepStage>3</SleepStage><SleepStage>2</SleepStage><SleepStage>3</SleepStage><SleepStage>3</SleepStage><SleepStage>3</SleepStage><SleepStage>2</SleepStage><SleepStage>3</SleepStage><SleepStage>3</SleepStage><SleepStage>3</SleepStage><SleepStage>3</SleepStage><SleepStage>2</SleepStage><SleepStage>3</SleepStage><SleepStage>3</SleepStage><SleepStage>2</SleepStage><SleepStage>2</SleepStage><SleepStage>5</SleepStage><SleepStage>5</SleepStage><SleepStage>5</SleepStage><SleepStage>5</SleepStage><SleepStage>0</SleepStage><SleepStage>0</SleepStage><SleepStage>0</SleepStage><SleepStage>0</SleepStage><SleepStage>1</SleepStage><SleepStage>1</SleepStage><SleepStage>1</SleepStage><SleepStage>5</SleepStage><SleepStage>5</SleepStage><SleepStage>5</SleepStage><SleepStage>5</SleepStage><SleepStage>5</SleepStage><SleepStage>5</SleepStage><SleepStage>5</SleepStage><SleepStage>5</SleepStage><SleepStage>5</SleepStage><SleepStage>5</SleepStage><SleepStage>5</SleepStage><SleepStage>5</SleepStage><SleepStage>0</SleepStage><SleepStage>5</SleepStage><SleepStage>5</SleepStage><SleepStage>5</SleepStage><SleepStage>5</SleepStage><SleepStage>5</SleepStage><SleepStage>5</SleepStage><SleepStage>5</SleepStage><SleepStage>5</SleepStage><SleepStage>5</SleepStage><SleepStage>5</SleepStage><SleepStage>5</SleepStage><SleepStage>5</SleepStage><SleepStage>5</SleepStage><SleepStage>5</SleepStage><SleepStage>5</SleepStage><SleepStage>5</SleepStage><SleepStage>5</SleepStage><SleepStage>5</SleepStage><SleepStage>5</SleepStage><SleepStage>5</SleepStage><SleepStage>5</SleepStage><SleepStage>5</SleepStage><SleepStage>5</SleepStage><SleepStage>5</SleepStage><SleepStage>5</SleepStage><SleepStage>5</SleepStage><SleepStage>5</SleepStage><SleepStage>5</SleepStage><SleepStage>5</SleepStage><SleepStage>5</SleepStage><SleepStage>5</SleepStage><SleepStage>5</SleepStage><SleepStage>5</SleepStage><SleepStage>5</SleepStage><SleepStage>5</SleepStage><SleepStage>5</SleepStage><SleepStage>5</SleepStage><SleepStage>0</SleepStage><SleepStage>1</SleepStage><SleepStage>2</SleepStage><SleepStage>2</SleepStage><SleepStage>2</SleepStage><SleepStage>2</SleepStage><SleepStage>2</SleepStage><SleepStage>2</SleepStage><SleepStage>2</SleepStage><SleepStage>2</SleepStage><SleepStage>2</SleepStage><SleepStage>2</SleepStage><SleepStage>2</SleepStage><SleepStage>2</SleepStage><SleepStage>2</SleepStage><SleepStage>2</SleepStage><SleepStage>2</SleepStage><SleepStage>2</SleepStage><SleepStage>2</SleepStage><SleepStage>2</SleepStage><SleepStage>2</SleepStage><SleepStage>3</SleepStage><SleepStage>3</SleepStage><SleepStage>3</SleepStage><SleepStage>2</SleepStage><SleepStage>2</SleepStage><SleepStage>3</SleepStage><SleepStage>2</SleepStage><SleepStage>2</SleepStage><SleepStage>2</SleepStage><SleepStage>3</SleepStage><SleepStage>2</SleepStage><SleepStage>2</SleepStage><SleepStage>3</SleepStage><SleepStage>3</SleepStage><SleepStage>3</SleepStage><SleepStage>2</SleepStage><SleepStage>3</SleepStage><SleepStage>2</SleepStage><SleepStage>2</SleepStage><SleepStage>2</SleepStage><SleepStage>2</SleepStage><SleepStage>3</SleepStage><SleepStage>2</SleepStage><SleepStage>2</SleepStage><SleepStage>3</SleepStage><SleepStage>2</SleepStage><SleepStage>2</SleepStage><SleepStage>2</SleepStage><SleepStage>2</SleepStage><SleepStage>2</SleepStage><SleepStage>2</SleepStage><SleepStage>3</SleepStage><SleepStage>2</SleepStage><SleepStage>2</SleepStage><SleepStage>3</SleepStage><SleepStage>3</SleepStage><SleepStage>3</SleepStage><SleepStage>3</SleepStage><SleepStage>3</SleepStage><SleepStage>3</SleepStage><SleepStage>3</SleepStage><SleepStage>3</SleepStage><SleepStage>3</SleepStage><SleepStage>2</SleepStage><SleepStage>3</SleepStage><SleepStage>3</SleepStage><SleepStage>2</SleepStage><SleepStage>3</SleepStage><SleepStage>3</SleepStage><SleepStage>3</SleepStage><SleepStage>3</SleepStage><SleepStage>3</SleepStage><SleepStage>3</SleepStage><SleepStage>3</SleepStage><SleepStage>3</SleepStage><SleepStage>3</SleepStage><SleepStage>3</SleepStage><SleepStage>3</SleepStage><SleepStage>3</SleepStage><SleepStage>3</SleepStage><SleepStage>3</SleepStage><SleepStage>3</SleepStage><SleepStage>3</SleepStage><SleepStage>2</SleepStage><SleepStage>3</SleepStage><SleepStage>2</SleepStage><SleepStage>3</SleepStage><SleepStage>3</SleepStage><SleepStage>3</SleepStage><SleepStage>2</SleepStage><SleepStage>3</SleepStage><SleepStage>3</SleepStage><SleepStage>3</SleepStage><SleepStage>3</SleepStage><SleepStage>3</SleepStage><SleepStage>3</SleepStage><SleepStage>3</SleepStage><SleepStage>3</SleepStage><SleepStage>3</SleepStage><SleepStage>2</SleepStage><SleepStage>2</SleepStage><SleepStage>2</SleepStage><SleepStage>2</SleepStage><SleepStage>3</SleepStage><SleepStage>2</SleepStage><SleepStage>2</SleepStage><SleepStage>2</SleepStage><SleepStage>2</SleepStage><SleepStage>2</SleepStage><SleepStage>2</SleepStage><SleepStage>2</SleepStage><SleepStage>2</SleepStage><SleepStage>2</SleepStage><SleepStage>2</SleepStage><SleepStage>2</SleepStage><SleepStage>2</SleepStage><SleepStage>2</SleepStage><SleepStage>2</SleepStage><SleepStage>5</SleepStage><SleepStage>5</SleepStage><SleepStage>5</SleepStage><SleepStage>5</SleepStage><SleepStage>5</SleepStage><SleepStage>5</SleepStage><SleepStage>5</SleepStage><SleepStage>5</SleepStage><SleepStage>5</SleepStage><SleepStage>5</SleepStage><SleepStage>5</SleepStage><SleepStage>5</SleepStage><SleepStage>5</SleepStage><SleepStage>5</SleepStage><SleepStage>5</SleepStage><SleepStage>5</SleepStage><SleepStage>5</SleepStage><SleepStage>5</SleepStage><SleepStage>5</SleepStage><SleepStage>5</SleepStage><SleepStage>5</SleepStage><SleepStage>5</SleepStage><SleepStage>0</SleepStage><SleepStage>1</SleepStage><SleepStage>1</SleepStage><SleepStage>1</SleepStage><SleepStage>2</SleepStage><SleepStage>2</SleepStage><SleepStage>2</SleepStage><SleepStage>2</SleepStage><SleepStage>2</SleepStage><SleepStage>2</SleepStage><SleepStage>2</SleepStage><SleepStage>2</SleepStage><SleepStage>2</SleepStage><SleepStage>2</SleepStage><SleepStage>2</SleepStage><SleepStage>2</SleepStage><SleepStage>2</SleepStage><SleepStage>2</SleepStage><SleepStage>2</SleepStage><SleepStage>2</SleepStage><SleepStage>2</SleepStage><SleepStage>2</SleepStage><SleepStage>2</SleepStage><SleepStage>2</SleepStage><SleepStage>2</SleepStage><SleepStage>2</SleepStage><SleepStage>2</SleepStage><SleepStage>2</SleepStage><SleepStage>2</SleepStage><SleepStage>2</SleepStage><SleepStage>2</SleepStage><SleepStage>2</SleepStage><SleepStage>2</SleepStage><SleepStage>2</SleepStage><SleepStage>2</SleepStage><SleepStage>2</SleepStage><SleepStage>2</SleepStage><SleepStage>2</SleepStage><SleepStage>2</SleepStage><SleepStage>2</SleepStage><SleepStage>2</SleepStage><SleepStage>2</SleepStage><SleepStage>2</SleepStage><SleepStage>2</SleepStage><SleepStage>2</SleepStage><SleepStage>2</SleepStage><SleepStage>2</SleepStage><SleepStage>2</SleepStage><SleepStage>2</SleepStage><SleepStage>2</SleepStage><SleepStage>2</SleepStage><SleepStage>2</SleepStage><SleepStage>2</SleepStage><SleepStage>2</SleepStage><SleepStage>2</SleepStage><SleepStage>2</SleepStage><SleepStage>2</SleepStage><SleepStage>2</SleepStage><SleepStage>2</SleepStage><SleepStage>2</SleepStage><SleepStage>2</SleepStage><SleepStage>2</SleepStage><SleepStage>2</SleepStage><SleepStage>2</SleepStage><SleepStage>2</SleepStage><SleepStage>2</SleepStage><SleepStage>2</SleepStage><SleepStage>2</SleepStage><SleepStage>2</SleepStage><SleepStage>2</SleepStage><SleepStage>2</SleepStage><SleepStage>2</SleepStage><SleepStage>2</SleepStage><SleepStage>0</SleepStage><SleepStage>1</SleepStage><SleepStage>0</SleepStage><SleepStage>1</SleepStage><SleepStage>0</SleepStage><SleepStage>1</SleepStage><SleepStage>1</SleepStage><SleepStage>0</SleepStage><SleepStage>0</SleepStage><SleepStage>0</SleepStage><SleepStage>0</SleepStage><SleepStage>0</SleepStage><SleepStage>1</SleepStage><SleepStage>2</SleepStage><SleepStage>2</SleepStage><SleepStage>0</SleepStage><SleepStage>0</SleepStage><SleepStage>0</SleepStage><SleepStage>0</SleepStage><SleepStage>0</SleepStage><SleepStage>0</SleepStage><SleepStage>0</SleepStage><SleepStage>0</SleepStage><SleepStage>0</SleepStage><SleepStage>0</SleepStage><SleepStage>0</SleepStage><SleepStage>1</SleepStage><SleepStage>1</SleepStage><SleepStage>2</SleepStage><SleepStage>2</SleepStage><SleepStage>2</SleepStage><SleepStage>2</SleepStage><SleepStage>2</SleepStage><SleepStage>2</SleepStage><SleepStage>2</SleepStage><SleepStage>2</SleepStage><SleepStage>2</SleepStage><SleepStage>2</SleepStage><SleepStage>2</SleepStage><SleepStage>5</SleepStage><SleepStage>5</SleepStage><SleepStage>5</SleepStage><SleepStage>5</SleepStage><SleepStage>5</SleepStage><SleepStage>5</SleepStage><SleepStage>5</SleepStage><SleepStage>5</SleepStage><SleepStage>5</SleepStage><SleepStage>5</SleepStage><SleepStage>5</SleepStage><SleepStage>5</SleepStage><SleepStage>5</SleepStage><SleepStage>5</SleepStage><SleepStage>5</SleepStage><SleepStage>5</SleepStage><SleepStage>5</SleepStage><SleepStage>5</SleepStage><SleepStage>5</SleepStage><SleepStage>5</SleepStage><SleepStage>5</SleepStage><SleepStage>5</SleepStage><SleepStage>5</SleepStage><SleepStage>5</SleepStage><SleepStage>5</SleepStage><SleepStage>5</SleepStage><SleepStage>5</SleepStage><SleepStage>5</SleepStage><SleepStage>5</SleepStage><SleepStage>5</SleepStage><SleepStage>5</SleepStage><SleepStage>5</SleepStage><SleepStage>5</SleepStage><SleepStage>5</SleepStage><SleepStage>5</SleepStage><SleepStage>5</SleepStage><SleepStage>5</SleepStage><SleepStage>5</SleepStage><SleepStage>5</SleepStage><SleepStage>5</SleepStage><SleepStage>5</SleepStage><SleepStage>5</SleepStage><SleepStage>5</SleepStage><SleepStage>5</SleepStage><SleepStage>5</SleepStage><SleepStage>5</SleepStage><SleepStage>5</SleepStage><SleepStage>5</SleepStage><SleepStage>5</SleepStage><SleepStage>5</SleepStage><SleepStage>5</SleepStage><SleepStage>5</SleepStage><SleepStage>5</SleepStage><SleepStage>5</SleepStage><SleepStage>5</SleepStage><SleepStage>5</SleepStage><SleepStage>5</SleepStage><SleepStage>5</SleepStage><SleepStage>5</SleepStage><SleepStage>5</SleepStage><SleepStage>5</SleepStage><SleepStage>5</SleepStage><SleepStage>5</SleepStage><SleepStage>5</SleepStage><SleepStage>0</SleepStage><SleepStage>2</SleepStage><SleepStage>2</SleepStage><SleepStage>2</SleepStage><SleepStage>2</SleepStage><SleepStage>2</SleepStage><SleepStage>2</SleepStage><SleepStage>2</SleepStage><SleepStage>2</SleepStage><SleepStage>2</SleepStage><SleepStage>2</SleepStage><SleepStage>2</SleepStage><SleepStage>2</SleepStage><SleepStage>2</SleepStage><SleepStage>2</SleepStage><SleepStage>2</SleepStage><SleepStage>2</SleepStage><SleepStage>2</SleepStage><SleepStage>2</SleepStage><SleepStage>2</SleepStage><SleepStage>2</SleepStage><SleepStage>2</SleepStage><SleepStage>2</SleepStage><SleepStage>2</SleepStage><SleepStage>2</SleepStage><SleepStage>2</SleepStage><SleepStage>2</SleepStage><SleepStage>2</SleepStage><SleepStage>2</SleepStage><SleepStage>2</SleepStage><SleepStage>2</SleepStage><SleepStage>2</SleepStage><SleepStage>2</SleepStage><SleepStage>2</SleepStage><SleepStage>2</SleepStage><SleepStage>2</SleepStage><SleepStage>2</SleepStage><SleepStage>0</SleepStage><SleepStage>2</SleepStage><SleepStage>2</SleepStage><SleepStage>2</SleepStage><SleepStage>2</SleepStage><SleepStage>2</SleepStage><SleepStage>2</SleepStage><SleepStage>2</SleepStage><SleepStage>2</SleepStage><SleepStage>2</SleepStage><SleepStage>2</SleepStage><SleepStage>2</SleepStage><SleepStage>2</SleepStage><SleepStage>2</SleepStage><SleepStage>2</SleepStage><SleepStage>2</SleepStage><SleepStage>2</SleepStage><SleepStage>2</SleepStage><SleepStage>2</SleepStage><SleepStage>2</SleepStage><SleepStage>3</SleepStage><SleepStage>2</SleepStage><SleepStage>2</SleepStage><SleepStage>2</SleepStage><SleepStage>2</SleepStage><SleepStage>2</SleepStage><SleepStage>2</SleepStage><SleepStage>2</SleepStage><SleepStage>2</SleepStage><SleepStage>2</SleepStage><SleepStage>3</SleepStage><SleepStage>3</SleepStage><SleepStage>2</SleepStage><SleepStage>2</SleepStage><SleepStage>2</SleepStage><SleepStage>2</SleepStage><SleepStage>2</SleepStage><SleepStage>2</SleepStage><SleepStage>2</SleepStage><SleepStage>2</SleepStage><SleepStage>2</SleepStage><SleepStage>2</SleepStage><SleepStage>2</SleepStage><SleepStage>0</SleepStage><SleepStage>0</SleepStage><SleepStage>0</SleepStage><SleepStage>1</SleepStage><SleepStage>0</SleepStage><SleepStage>1</SleepStage><SleepStage>2</SleepStage><SleepStage>2</SleepStage><SleepStage>2</SleepStage><SleepStage>2</SleepStage><SleepStage>0</SleepStage><SleepStage>0</SleepStage><SleepStage>0</SleepStage><SleepStage>1</SleepStage><SleepStage>0</SleepStage><SleepStage>1</SleepStage><SleepStage>2</SleepStage><SleepStage>0</SleepStage><SleepStage>2</SleepStage><SleepStage>2</SleepStage><SleepStage>2</SleepStage><SleepStage>2</SleepStage><SleepStage>2</SleepStage><SleepStage>2</SleepStage><SleepStage>2</SleepStage><SleepStage>2</SleepStage><SleepStage>2</SleepStage><SleepStage>5</SleepStage><SleepStage>5</SleepStage><SleepStage>5</SleepStage><SleepStage>5</SleepStage><SleepStage>5</SleepStage><SleepStage>5</SleepStage><SleepStage>5</SleepStage><SleepStage>5</SleepStage><SleepStage>5</SleepStage><SleepStage>5</SleepStage><SleepStage>5</SleepStage><SleepStage>5</SleepStage><SleepStage>5</SleepStage><SleepStage>5</SleepStage><SleepStage>5</SleepStage><SleepStage>5</SleepStage><SleepStage>5</SleepStage><SleepStage>5</SleepStage><SleepStage>5</SleepStage><SleepStage>5</SleepStage><SleepStage>5</SleepStage><SleepStage>5</SleepStage><SleepStage>5</SleepStage><SleepStage>5</SleepStage><SleepStage>5</SleepStage><SleepStage>5</SleepStage><SleepStage>5</SleepStage><SleepStage>5</SleepStage><SleepStage>5</SleepStage><SleepStage>5</SleepStage><SleepStage>5</SleepStage><SleepStage>5</SleepStage><SleepStage>5</SleepStage><SleepStage>5</SleepStage><SleepStage>5</SleepStage><SleepStage>5</SleepStage><SleepStage>5</SleepStage><SleepStage>5</SleepStage><SleepStage>5</SleepStage><SleepStage>5</SleepStage><SleepStage>5</SleepStage><SleepStage>5</SleepStage><SleepStage>5</SleepStage><SleepStage>5</SleepStage><SleepStage>5</SleepStage><SleepStage>5</SleepStage><SleepStage>5</SleepStage><SleepStage>5</SleepStage><SleepStage>5</SleepStage><SleepStage>5</SleepStage><SleepStage>5</SleepStage><SleepStage>5</SleepStage><SleepStage>5</SleepStage><SleepStage>5</SleepStage><SleepStage>5</SleepStage><SleepStage>5</SleepStage><SleepStage>5</SleepStage><SleepStage>5</SleepStage><SleepStage>5</SleepStage><SleepStage>5</SleepStage><SleepStage>5</SleepStage><SleepStage>5</SleepStage><SleepStage>5</SleepStage><SleepStage>5</SleepStage><SleepStage>5</SleepStage><SleepStage>5</SleepStage><SleepStage>5</SleepStage><SleepStage>5</SleepStage><SleepStage>5</SleepStage><SleepStage>5</SleepStage><SleepStage>5</SleepStage><SleepStage>5</SleepStage><SleepStage>5</SleepStage><SleepStage>5</SleepStage><SleepStage>5</SleepStage><SleepStage>5</SleepStage><SleepStage>5</SleepStage><SleepStage>5</SleepStage><SleepStage>5</SleepStage><SleepStage>5</SleepStage><SleepStage>5</SleepStage><SleepStage>5</SleepStage><SleepStage>5</SleepStage><SleepStage>5</SleepStage><SleepStage>5</SleepStage><SleepStage>2</SleepStage><SleepStage>2</SleepStage><SleepStage>2</SleepStage><SleepStage>2</SleepStage><SleepStage>2</SleepStage><SleepStage>2</SleepStage><SleepStage>2</SleepStage><SleepStage>2</SleepStage><SleepStage>2</SleepStage><SleepStage>2</SleepStage><SleepStage>2</SleepStage><SleepStage>2</SleepStage><SleepStage>2</SleepStage><SleepStage>2</SleepStage><SleepStage>2</SleepStage><SleepStage>2</SleepStage><SleepStage>2</SleepStage><SleepStage>0</SleepStage><SleepStage>0</SleepStage><SleepStage>0</SleepStage><SleepStage>1</SleepStage><SleepStage>1</SleepStage><SleepStage>1</SleepStage><SleepStage>1</SleepStage><SleepStage>2</SleepStage><SleepStage>2</SleepStage><SleepStage>2</SleepStage><SleepStage>2</SleepStage><SleepStage>2</SleepStage><SleepStage>2</SleepStage><SleepStage>2</SleepStage><SleepStage>2</SleepStage><SleepStage>2</SleepStage><SleepStage>2</SleepStage><SleepStage>2</SleepStage><SleepStage>2</SleepStage><SleepStage>2</SleepStage><SleepStage>2</SleepStage><SleepStage>2</SleepStage><SleepStage>2</SleepStage><SleepStage>2</SleepStage><SleepStage>2</SleepStage><SleepStage>2</SleepStage><SleepStage>2</SleepStage><SleepStage>2</SleepStage><SleepStage>2</SleepStage><SleepStage>2</SleepStage><SleepStage>2</SleepStage><SleepStage>2</SleepStage><SleepStage>2</SleepStage><SleepStage>2</SleepStage><SleepStage>2</SleepStage><SleepStage>2</SleepStage><SleepStage>2</SleepStage><SleepStage>2</SleepStage><SleepStage>2</SleepStage><SleepStage>0</SleepStage><SleepStage>0</SleepStage><SleepStage>2</SleepStage><SleepStage>2</SleepStage><SleepStage>2</SleepStage><SleepStage>2</SleepStage><SleepStage>2</SleepStage><SleepStage>2</SleepStage><SleepStage>2</SleepStage><SleepStage>0</SleepStage><SleepStage>0</SleepStage><SleepStage>1</SleepStage><SleepStage>1</SleepStage><SleepStage>1</SleepStage><SleepStage>1</SleepStage><SleepStage>1</SleepStage><SleepStage>1</SleepStage><SleepStage>2</SleepStage><SleepStage>2</SleepStage><SleepStage>2</SleepStage><SleepStage>2</SleepStage><SleepStage>2</SleepStage><SleepStage>2</SleepStage><SleepStage>2</SleepStage><SleepStage>2</SleepStage><SleepStage>2</SleepStage><SleepStage>2</SleepStage><SleepStage>2</SleepStage><SleepStage>2</SleepStage><SleepStage>2</SleepStage><SleepStage>2</SleepStage><SleepStage>2</SleepStage><SleepStage>2</SleepStage><SleepStage>2</SleepStage><SleepStage>2</SleepStage><SleepStage>2</SleepStage><SleepStage>2</SleepStage><SleepStage>2</SleepStage><SleepStage>2</SleepStage><SleepStage>2</SleepStage><SleepStage>2</SleepStage><SleepStage>2</SleepStage><SleepStage>2</SleepStage><SleepStage>0</SleepStage><SleepStage>0</SleepStage><SleepStage>1</SleepStage><SleepStage>1</SleepStage><SleepStage>1</SleepStage><SleepStage>1</SleepStage><SleepStage>2</SleepStage><SleepStage>2</SleepStage><SleepStage>2</SleepStage><SleepStage>2</SleepStage><SleepStage>2</SleepStage><SleepStage>2</SleepStage><SleepStage>2</SleepStage><SleepStage>2</SleepStage><SleepStage>2</SleepStage><SleepStage>2</SleepStage><SleepStage>2</SleepStage><SleepStage>2</SleepStage><SleepStage>2</SleepStage><SleepStage>2</SleepStage><SleepStage>2</SleepStage><SleepStage>2</SleepStage><SleepStage>2</SleepStage><SleepStage>2</SleepStage><SleepStage>2</SleepStage><SleepStage>2</SleepStage><SleepStage>2</SleepStage><SleepStage>2</SleepStage><SleepStage>2</SleepStage><SleepStage>2</SleepStage><SleepStage>2</SleepStage><SleepStage>2</SleepStage><SleepStage>2</SleepStage><SleepStage>2</SleepStage><SleepStage>2</SleepStage><SleepStage>2</SleepStage><SleepStage>2</SleepStage><SleepStage>2</SleepStage><SleepStage>2</SleepStage><SleepStage>2</SleepStage><SleepStage>2</SleepStage><SleepStage>2</SleepStage><SleepStage>2</SleepStage><SleepStage>2</SleepStage><SleepStage>2</SleepStage><SleepStage>2</SleepStage><SleepStage>0</SleepStage><SleepStage>1</SleepStage><SleepStage>2</SleepStage><SleepStage>0</SleepStage><SleepStage>0</SleepStage><SleepStage>0</SleepStage><SleepStage>1</SleepStage><SleepStage>0</SleepStage><SleepStage>0</SleepStage><SleepStage>0</SleepStage><SleepStage>0</SleepStage><SleepStage>0</SleepStage><SleepStage>0</SleepStage><SleepStage>0</SleepStage><SleepStage>0</SleepStage><SleepStage>0</SleepStage><SleepStage>0</SleepStage><SleepStage>0</SleepStage><SleepStage>0</SleepStage><SleepStage>0</SleepStage><SleepStage>0</SleepStage><SleepStage>0</SleepStage><SleepStage>0</SleepStage><SleepStage>0</SleepStage><SleepStage>0</SleepStage><SleepStage>0</SleepStage><SleepStage>0</SleepStage><SleepStage>0</SleepStage><SleepStage>0</SleepStage><SleepStage>0</SleepStage><SleepStage>0</SleepStage><SleepStage>0</SleepStage><SleepStage>0</SleepStage><SleepStage>0</SleepStage><SleepStage>0</SleepStage><SleepStage>0</SleepStage><SleepStage>0</SleepStage><SleepStage>0</SleepStage><SleepStage>0</SleepStage><SleepStage>0</SleepStage><SleepStage>0</SleepStage><SleepStage>0</SleepStage><SleepStage>0</SleepStage><SleepStage>0</SleepStage><SleepStage>0</SleepStage><SleepStage>0</SleepStage><SleepStage>0</SleepStage><SleepStage>0</SleepStage><SleepStage>0</SleepStage><SleepStage>0</SleepStage><SleepStage>0</SleepStage><SleepStage>0</SleepStage><SleepStage>0</SleepStage><SleepStage>0</SleepStage><SleepStage>0</SleepStage><SleepStage>0</SleepStage><SleepStage>0</SleepStage><SleepStage>0</SleepStage><SleepStage>0</SleepStage><SleepStage>0</SleepStage><SleepStage>0</SleepStage><SleepStage>0</SleepStage><SleepStage>0</SleepStage><SleepStage>0</SleepStage><SleepStage>0</SleepStage><SleepStage>0</SleepStage><SleepStage>0</SleepStage><SleepStage>0</SleepStage><SleepStage>0</SleepStage><SleepStage>0</SleepStage><SleepStage>0</SleepStage><SleepStage>0</SleepStage><SleepStage>0</SleepStage><SleepStage>0</SleepStage><SleepStage>0</SleepStage><SleepStage>0</SleepStage><SleepStage>0</SleepStage><SleepStage>0</SleepStage><SleepStage>0</SleepStage><SleepStage>0</SleepStage><SleepStage>0</SleepStage><SleepStage>0</SleepStage><SleepStage>0</SleepStage><SleepStage>0</SleepStage><SleepStage>0</SleepStage><SleepStage>0</SleepStage><SleepStage>0</SleepStage><SleepStage>0</SleepStage><SleepStage>0</SleepStage><SleepStage>0</SleepStage><SleepStage>0</SleepStage><SleepStage>0</SleepStage><SleepStage>0</SleepStage><SleepStage>0</SleepStage><SleepStage>0</SleepStage><SleepStage>0</SleepStage><SleepStage>0</SleepStage><SleepStage>0</SleepStage><SleepStage>0</SleepStage><SleepStage>0</SleepStage><SleepStage>0</SleepStage><SleepStage>0</SleepStage><SleepStage>0</SleepStage><SleepStage>0</SleepStage><SleepStage>0</SleepStage><SleepStage>0</SleepStage><SleepStage>0</SleepStage><SleepStage>0</SleepStage><SleepStage>0</SleepStage><SleepStage>0</SleepStage><SleepStage>0</SleepStage><SleepStage>0</SleepStage><SleepStage>0</SleepStage><SleepStage>0</SleepStage><SleepStage>0</SleepStage><SleepStage>0</SleepStage><SleepStage>0</SleepStage><SleepStage>0</SleepStage><SleepStage>0</SleepStage><SleepStage>0</SleepStage><SleepStage>0</SleepStage><SleepStage>0</SleepStage><SleepStage>0</SleepStage><SleepStage>0</SleepStage><SleepStage>0</SleepStage><SleepStage>0</SleepStage><SleepStage>0</SleepStage><SleepStage>0</SleepStage><SleepStage>0</SleepStage><SleepStage>0</SleepStage><SleepStage>0</SleepStage><SleepStage>0</SleepStage><SleepStage>0</SleepStage><SleepStage>0</SleepStage><SleepStage>0</SleepStage><SleepStage>0</SleepStage><SleepStage>0</SleepStage><SleepStage>0</SleepStage><SleepStage>0</SleepStage><SleepStage>0</SleepStage><SleepStage>0</SleepStage><SleepStage>0</SleepStage><SleepStage>0</SleepStage><SleepStage>0</SleepStage><SleepStage>0</SleepStage><SleepStage>0</SleepStage><SleepStage>0</SleepStage><SleepStage>0</SleepStage><SleepStage>0</SleepStage><SleepStage>0</SleepStage><SleepStage>0</SleepStage><SleepStage>0</SleepStage><SleepStage>0</SleepStage><SleepStage>0</SleepStage><SleepStage>0</SleepStage><SleepStage>0</SleepStage><SleepStage>0</SleepStage><SleepStage>0</SleepStage><SleepStage>0</SleepStage><SleepStage>0</SleepStage><SleepStage>0</SleepStage><SleepStage>0</SleepStage><SleepStage>0</SleepStage><SleepStage>0</SleepStage><SleepStage>0</SleepStage><SleepStage>0</SleepStage><SleepStage>0</SleepStage><SleepStage>0</SleepStage><SleepStage>0</SleepStage><SleepStage>0</SleepStage><SleepStage>0</SleepStage><SleepStage>0</SleepStage><SleepStage>0</SleepStage><SleepStage>0</SleepStage><SleepStage>0</SleepStage><SleepStage>0</SleepStage><SleepStage>0</SleepStage><SleepStage>0</SleepStage><SleepStage>0</SleepStage><SleepStage>0</SleepStage><SleepStage>0</SleepStage><SleepStage>0</SleepStage><SleepStage>0</SleepStage><SleepStage>0</SleepStage><SleepStage>0</SleepStage><SleepStage>0</SleepStage><SleepStage>0</SleepStage><SleepStage>0</SleepStage><SleepStage>0</SleepStage><SleepStage>0</SleepStage><SleepStage>0</SleepStage><SleepStage>0</SleepStage><SleepStage>0</SleepStage><SleepStage>0</SleepStage><SleepStage>0</SleepStage><SleepStage>0</SleepStage><SleepStage>0</SleepStage><SleepStage>0</SleepStage><SleepStage>0</SleepStage><SleepStage>0</SleepStage><SleepStage>0</SleepStage><SleepStage>0</SleepStage><SleepStage>0</SleepStage><SleepStage>0</SleepStage><SleepStage>0</SleepStage><SleepStage>0</SleepStage><SleepStage>0</SleepStage><SleepStage>0</SleepStage><SleepStage>0</SleepStage></SleepStages><Montage><TracePanes><TracePane><BkColour>16777215</BkColour><Timebase>30</Timebase><BkColour>16777215</BkColour><Timebase>30</Timebase><Traces><Trace><Colour>0</Colour><HighPass>0</HighPass><Input>EOG(L)</Input><Ref></Ref><LowerLimit>-125.000005937181</LowerLimit><LowPass>0</LowPass><Notch>0</Notch><NumGridLines>0</NumGridLines><RelativeSize>1</RelativeSize><UpperLimit>125.000005937181</UpperLimit><Zoom>1</Zoom></Trace><Trace><Colour>0</Colour><HighPass>0</HighPass><Input>EOG(R)</Input><Ref></Ref><LowerLimit>-125.000005937181</LowerLimit><LowPass>0</LowPass><Notch>0</Notch><NumGridLines>0</NumGridLines><RelativeSize>1</RelativeSize><UpperLimit>125.000005937181</UpperLimit><Zoom>1</Zoom></Trace><Trace><Colour>0</Colour><HighPass>0</HighPass><Input>EMG</Input><Ref></Ref><LowerLimit>-31.4999997499399</LowerLimit><LowPass>0</LowPass><Notch>0</Notch><NumGridLines>0</NumGridLines><RelativeSize>1</RelativeSize><UpperLimit>31.4999997499399</UpperLimit><Zoom>1</Zoom></Trace><Trace><Colour>0</Colour><HighPass>0</HighPass><Input>EEG</Input><Ref></Ref><LowerLimit>-125.000005937181</LowerLimit><LowPass>0</LowPass><Notch>0</Notch><NumGridLines>0</NumGridLines><RelativeSize>1</RelativeSize><UpperLimit>125.000005937181</UpperLimit><Zoom>1</Zoom></Trace><Trace><Colour>0</Colour><HighPass>0</HighPass><Input>EEG(sec)</Input><Ref></Ref><LowerLimit>-125.000005937181</LowerLimit><LowPass>0</LowPass><Notch>0</Notch><NumGridLines>0</NumGridLines><RelativeSize>1</RelativeSize><UpperLimit>125.000005937181</UpperLimit><Zoom>1</Zoom></Trace><Trace><Colour>0</Colour><HighPass>0</HighPass><Input>ECG</Input><Ref></Ref><LowerLimit>-1.24999997206032</LowerLimit><LowPass>0</LowPass><Notch>0</Notch><NumGridLines>0</NumGridLines><RelativeSize>1</RelativeSize><UpperLimit>1.24999997206032</UpperLimit><Zoom>1</Zoom></Trace><Trace><Colour>0</Colour><HighPass>0</HighPass><Input>PR</Input><Ref></Ref><LowerLimit>50</LowerLimit><LowPass>0</LowPass><Notch>0</Notch><NumGridLines>5</NumGridLines><RelativeSize>1</RelativeSize><UpperLimit>90</UpperLimit><Zoom>1</Zoom></Trace><Trace><Colour>0</Colour><HighPass>0</HighPass><Input>AIRFLOW</Input><Ref></Ref><LowerLimit>-4</LowerLimit><LowPass>0</LowPass><Notch>0</Notch><NumGridLines>0</NumGridLines><RelativeSize>1</RelativeSize><UpperLimit>4</UpperLimit><Zoom>1</Zoom></Trace><Trace><Colour>0</Colour><HighPass>0</HighPass><Input>THOR RES</Input><Ref></Ref><LowerLimit>-4</LowerLimit><LowPass>0</LowPass><Notch>0</Notch><NumGridLines>0</NumGridLines><RelativeSize>1</RelativeSize><UpperLimit>4</UpperLimit><Zoom>1</Zoom></Trace><Trace><Colour>0</Colour><HighPass>0</HighPass><Input>ABDO RES</Input><Ref></Ref><LowerLimit>-4</LowerLimit><LowPass>0</LowPass><Notch>0</Notch><NumGridLines>0</NumGridLines><RelativeSize>1</RelativeSize><UpperLimit>4</UpperLimit><Zoom>1</Zoom></Trace><Trace><Colour>0</Colour><HighPass>0</HighPass><Input>SaO2</Input><Ref></Ref><LowerLimit>50</LowerLimit><LowPass>0</LowPass><Notch>0</Notch><NumGridLines>6</NumGridLines><RelativeSize>1</RelativeSize><UpperLimit>100</UpperLimit><Zoom>1</Zoom></Trace><Trace><Colour>0</Colour><HighPass>0</HighPass><Input>POSITION</Input><Ref></Ref><LowerLimit>0</LowerLimit><LowPass>0</LowPass><Notch>0</Notch><NumGridLines>1</NumGridLines><RelativeSize>1</RelativeSize><UpperLimit>3</UpperLimit><Zoom>1</Zoom></Trace><Trace><Colour>0</Colour><HighPass>0</HighPass><Input>LIGHT</Input><Ref></Ref><LowerLimit>0</LowerLimit><LowPass>0</LowPass><Notch>0</Notch><NumGridLines>1</NumGridLines><RelativeSize>1</RelativeSize><UpperLimit>1</UpperLimit><Zoom>1</Zoom></Trace></Traces></TracePane></TracePanes></Montage></CMPStudyConfig>
